Workbook
Name _Toc89451387: 'CAF Effort'!$B$2
Name _Toc89451388: 'CAF Effort'!$B$213

Sheet Effort Estimation
A1: Theme | B1: EPIC | C1: User Stories | D1: Task | E1: Point Value | F1: ~ Effort in Man Days | G1: Roles
A2: DI Upgrade | E2: 0 | F2: 0 | G2: .Net Developer
B3: Login | C3: Authentication | E3: 8 | F3: =IF(Table1[[#This Row],[Point Value]]=1,1,IF(Table1[[#This Row],[Point Value]]=2,2,IF(Table1[[#This Row],[Point Value]]=3,3,IF(Table1[[#This Row],[Point Value]]=5,4, IF(Table1[[#This Row],[Point Value]]=8,5, IF(Table1[[#This Row],[Point Value]]=13,10, IF(Table1[[#This Row],[Point Value]]=20, 15,IF(Table1[[#This Row],[Point Value]]=40,40)))))))) -> 5 | G3: .Net Developer
C4: SSO Inegration | E4: 8 | F4: =IF(Table1[[#This Row],[Point Value]]=1,1,IF(Table1[[#This Row],[Point Value]]=2,2,IF(Table1[[#This Row],[Point Value]]=3,3,IF(Table1[[#This Row],[Point Value]]=5,4, IF(Table1[[#This Row],[Point Value]]=8,5, IF(Table1[[#This Row],[Point Value]]=13,10, IF(Table1[[#This Row],[Point Value]]=20, 15,IF(Table1[[#This Row],[Point Value]]=40,40)))))))) -> 5 | G4: .Net Developer
C5: Authorization
C6: Passwod Management | E6: 5 | F6: =IF(Table1[[#This Row],[Point Value]]=1,1,IF(Table1[[#This Row],[Point Value]]=2,2,IF(Table1[[#This Row],[Point Value]]=3,3,IF(Table1[[#This Row],[Point Value]]=5,4, IF(Table1[[#This Row],[Point Value]]=8,5, IF(Table1[[#This Row],[Point Value]]=13,10, IF(Table1[[#This Row],[Point Value]]=20, 15,IF(Table1[[#This Row],[Point Value]]=40,40)))))))) -> 4 | G6: .Net Developer
B7: Dashboard | C7: Dashboard | E7: 8 | F7: =IF(Table1[[#This Row],[Point Value]]=1,1,IF(Table1[[#This Row],[Point Value]]=2,2,IF(Table1[[#This Row],[Point Value]]=3,3,IF(Table1[[#This Row],[Point Value]]=5,4, IF(Table1[[#This Row],[Point Value]]=8,5, IF(Table1[[#This Row],[Point Value]]=13,10, IF(Table1[[#This Row],[Point Value]]=20, 15,IF(Table1[[#This Row],[Point Value]]=40,40)))))))) -> 5 | G7: .Net Developer
C8: Reports | E8: 8 | F8: =IF(Table1[[#This Row],[Point Value]]=1,1,IF(Table1[[#This Row],[Point Value]]=2,2,IF(Table1[[#This Row],[Point Value]]=3,3,IF(Table1[[#This Row],[Point Value]]=5,4, IF(Table1[[#This Row],[Point Value]]=8,5, IF(Table1[[#This Row],[Point Value]]=13,10, IF(Table1[[#This Row],[Point Value]]=20, 15,IF(Table1[[#This Row],[Point Value]]=40,40)))))))) -> 5 | G8: .Net Developer
C9: Search | E9: 8 | F9: =IF(Table1[[#This Row],[Point Value]]=1,1,IF(Table1[[#This Row],[Point Value]]=2,2,IF(Table1[[#This Row],[Point Value]]=3,3,IF(Table1[[#This Row],[Point Value]]=5,4, IF(Table1[[#This Row],[Point Value]]=8,5, IF(Table1[[#This Row],[Point Value]]=13,10, IF(Table1[[#This Row],[Point Value]]=20, 15,IF(Table1[[#This Row],[Point Value]]=40,40)))))))) -> 5 | G9: .Net Developer
C10: Report Export | E10: 5 | F10: =IF(Table1[[#This Row],[Point Value]]=1,1,IF(Table1[[#This Row],[Point Value]]=2,2,IF(Table1[[#This Row],[Point Value]]=3,3,IF(Table1[[#This Row],[Point Value]]=5,4, IF(Table1[[#This Row],[Point Value]]=8,5, IF(Table1[[#This Row],[Point Value]]=13,10, IF(Table1[[#This Row],[Point Value]]=20, 15,IF(Table1[[#This Row],[Point Value]]=40,40)))))))) -> 4 | G10: .Net Developer
C11: Audit Logs | E11: 13 | F11: =IF(Table1[[#This Row],[Point Value]]=1,1,IF(Table1[[#This Row],[Point Value]]=2,2,IF(Table1[[#This Row],[Point Value]]=3,3,IF(Table1[[#This Row],[Point Value]]=5,4, IF(Table1[[#This Row],[Point Value]]=8,5, IF(Table1[[#This Row],[Point Value]]=13,10, IF(Table1[[#This Row],[Point Value]]=20, 15,IF(Table1[[#This Row],[Point Value]]=40,40)))))))) -> 10 | G11: .Net Developer
B12: Maintenance | C12: Approver List | E12: 8 | F12: =IF(Table1[[#This Row],[Point Value]]=1,1,IF(Table1[[#This Row],[Point Value]]=2,2,IF(Table1[[#This Row],[Point Value]]=3,3,IF(Table1[[#This Row],[Point Value]]=5,4, IF(Table1[[#This Row],[Point Value]]=8,5, IF(Table1[[#This Row],[Point Value]]=13,10, IF(Table1[[#This Row],[Point Value]]=20, 15,IF(Table1[[#This Row],[Point Value]]=40,40)))))))) -> 5 | G12: .Net Developer
C13: Customer | E13: 8 | F13: =IF(Table1[[#This Row],[Point Value]]=1,1,IF(Table1[[#This Row],[Point Value]]=2,2,IF(Table1[[#This Row],[Point Value]]=3,3,IF(Table1[[#This Row],[Point Value]]=5,4, IF(Table1[[#This Row],[Point Value]]=8,5, IF(Table1[[#This Row],[Point Value]]=13,10, IF(Table1[[#This Row],[Point Value]]=20, 15,IF(Table1[[#This Row],[Point Value]]=40,40)))))))) -> 5 | G13: .Net Developer
C14: Customer Group | E14: 8 | F14: =IF(Table1[[#This Row],[Point Value]]=1,1,IF(Table1[[#This Row],[Point Value]]=2,2,IF(Table1[[#This Row],[Point Value]]=3,3,IF(Table1[[#This Row],[Point Value]]=5,4, IF(Table1[[#This Row],[Point Value]]=8,5, IF(Table1[[#This Row],[Point Value]]=13,10, IF(Table1[[#This Row],[Point Value]]=20, 15,IF(Table1[[#This Row],[Point Value]]=40,40)))))))) -> 5 | G14: .Net Developer
C15: Configuration | E15: 8 | F15: =IF(Table1[[#This Row],[Point Value]]=1,1,IF(Table1[[#This Row],[Point Value]]=2,2,IF(Table1[[#This Row],[Point Value]]=3,3,IF(Table1[[#This Row],[Point Value]]=5,4, IF(Table1[[#This Row],[Point Value]]=8,5, IF(Table1[[#This Row],[Point Value]]=13,10, IF(Table1[[#This Row],[Point Value]]=20, 15,IF(Table1[[#This Row],[Point Value]]=40,40)))))))) -> 5 | G15: .Net Developer
C16: Commercial Unit | E16: 8 | F16: =IF(Table1[[#This Row],[Point Value]]=1,1,IF(Table1[[#This Row],[Point Value]]=2,2,IF(Table1[[#This Row],[Point Value]]=3,3,IF(Table1[[#This Row],[Point Value]]=5,4, IF(Table1[[#This Row],[Point Value]]=8,5, IF(Table1[[#This Row],[Point Value]]=13,10, IF(Table1[[#This Row],[Point Value]]=20, 15,IF(Table1[[#This Row],[Point Value]]=40,40)))))))) -> 5 | G16: .Net Developer
C17: Invoice Footer | E17: 5 | F17: =IF(Table1[[#This Row],[Point Value]]=1,1,IF(Table1[[#This Row],[Point Value]]=2,2,IF(Table1[[#This Row],[Point Value]]=3,3,IF(Table1[[#This Row],[Point Value]]=5,4, IF(Table1[[#This Row],[Point Value]]=8,5, IF(Table1[[#This Row],[Point Value]]=13,10, IF(Table1[[#This Row],[Point Value]]=20, 15,IF(Table1[[#This Row],[Point Value]]=40,40)))))))) -> 4 | G17: .Net Developer
C18: Location | E18: 5 | F18: =IF(Table1[[#This Row],[Point Value]]=1,1,IF(Table1[[#This Row],[Point Value]]=2,2,IF(Table1[[#This Row],[Point Value]]=3,3,IF(Table1[[#This Row],[Point Value]]=5,4, IF(Table1[[#This Row],[Point Value]]=8,5, IF(Table1[[#This Row],[Point Value]]=13,10, IF(Table1[[#This Row],[Point Value]]=20, 15,IF(Table1[[#This Row],[Point Value]]=40,40)))))))) -> 4 | G18: .Net Developer
C19: Sales Group | E19: 5 | F19: =IF(Table1[[#This Row],[Point Value]]=1,1,IF(Table1[[#This Row],[Point Value]]=2,2,IF(Table1[[#This Row],[Point Value]]=3,3,IF(Table1[[#This Row],[Point Value]]=5,4, IF(Table1[[#This Row],[Point Value]]=8,5, IF(Table1[[#This Row],[Point Value]]=13,10, IF(Table1[[#This Row],[Point Value]]=20, 15,IF(Table1[[#This Row],[Point Value]]=40,40)))))))) -> 4 | G19: .Net Developer
C20: Sales Office | E20: 5 | F20: =IF(Table1[[#This Row],[Point Value]]=1,1,IF(Table1[[#This Row],[Point Value]]=2,2,IF(Table1[[#This Row],[Point Value]]=3,3,IF(Table1[[#This Row],[Point Value]]=5,4, IF(Table1[[#This Row],[Point Value]]=8,5, IF(Table1[[#This Row],[Point Value]]=13,10, IF(Table1[[#This Row],[Point Value]]=20, 15,IF(Table1[[#This Row],[Point Value]]=40,40)))))))) -> 4 | G20: .Net Developer
C21: Sales Org | E21: 5 | F21: =IF(Table1[[#This Row],[Point Value]]=1,1,IF(Table1[[#This Row],[Point Value]]=2,2,IF(Table1[[#This Row],[Point Value]]=3,3,IF(Table1[[#This Row],[Point Value]]=5,4, IF(Table1[[#This Row],[Point Value]]=8,5, IF(Table1[[#This Row],[Point Value]]=13,10, IF(Table1[[#This Row],[Point Value]]=20, 15,IF(Table1[[#This Row],[Point Value]]=40,40)))))))) -> 4 | G21: .Net Developer
C22: Site Admin | E22: 5 | F22: =IF(Table1[[#This Row],[Point Value]]=1,1,IF(Table1[[#This Row],[Point Value]]=2,2,IF(Table1[[#This Row],[Point Value]]=3,3,IF(Table1[[#This Row],[Point Value]]=5,4, IF(Table1[[#This Row],[Point Value]]=8,5, IF(Table1[[#This Row],[Point Value]]=13,10, IF(Table1[[#This Row],[Point Value]]=20, 15,IF(Table1[[#This Row],[Point Value]]=40,40)))))))) -> 4 | G22: .Net Developer
B23: Cloud Development | C23: Setting up MS Defender | E23: 8 | F23: =IF(Table1[[#This Row],[Point Value]]=1,1,IF(Table1[[#This Row],[Point Value]]=2,2,IF(Table1[[#This Row],[Point Value]]=3,3,IF(Table1[[#This Row],[Point Value]]=5,4, IF(Table1[[#This Row],[Point Value]]=8,5, IF(Table1[[#This Row],[Point Value]]=13,10, IF(Table1[[#This Row],[Point Value]]=20, 15,IF(Table1[[#This Row],[Point Value]]=40,40)))))))) -> 5 | G23: Azure Developer
C24: Setting up Azure Storage | E24: 8 | F24: =IF(Table1[[#This Row],[Point Value]]=1,1,IF(Table1[[#This Row],[Point Value]]=2,2,IF(Table1[[#This Row],[Point Value]]=3,3,IF(Table1[[#This Row],[Point Value]]=5,4, IF(Table1[[#This Row],[Point Value]]=8,5, IF(Table1[[#This Row],[Point Value]]=13,10, IF(Table1[[#This Row],[Point Value]]=20, 15,IF(Table1[[#This Row],[Point Value]]=40,40)))))))) -> 5 | G24: Azure Developer
B25: UX | C25: UI Design | E25: 40 | F25: =IF(Table1[[#This Row],[Point Value]]=1,1,IF(Table1[[#This Row],[Point Value]]=2,2,IF(Table1[[#This Row],[Point Value]]=3,3,IF(Table1[[#This Row],[Point Value]]=5,4, IF(Table1[[#This Row],[Point Value]]=8,5, IF(Table1[[#This Row],[Point Value]]=13,10, IF(Table1[[#This Row],[Point Value]]=20, 15,IF(Table1[[#This Row],[Point Value]]=40,40)))))))) -> 40 | G25: UX Developer
C26: JS Development | E26: 13 | F26: =IF(Table1[[#This Row],[Point Value]]=1,1,IF(Table1[[#This Row],[Point Value]]=2,2,IF(Table1[[#This Row],[Point Value]]=3,3,IF(Table1[[#This Row],[Point Value]]=5,4, IF(Table1[[#This Row],[Point Value]]=8,5, IF(Table1[[#This Row],[Point Value]]=13,10, IF(Table1[[#This Row],[Point Value]]=20, 15,IF(Table1[[#This Row],[Point Value]]=40,40)))))))) -> 10 | G26: UX Developer
B27: Testing | C27: Unit Testing | E27: 13 | F27: =IF(Table1[[#This Row],[Point Value]]=1,1,IF(Table1[[#This Row],[Point Value]]=2,2,IF(Table1[[#This Row],[Point Value]]=3,3,IF(Table1[[#This Row],[Point Value]]=5,4, IF(Table1[[#This Row],[Point Value]]=8,5, IF(Table1[[#This Row],[Point Value]]=13,10, IF(Table1[[#This Row],[Point Value]]=20, 15,IF(Table1[[#This Row],[Point Value]]=40,40)))))))) -> 10 | G27: .Net Developer
C28: SIT | E28: 40 | F28: =IF(Table1[[#This Row],[Point Value]]=1,1,IF(Table1[[#This Row],[Point Value]]=2,2,IF(Table1[[#This Row],[Point Value]]=3,3,IF(Table1[[#This Row],[Point Value]]=5,4, IF(Table1[[#This Row],[Point Value]]=8,5, IF(Table1[[#This Row],[Point Value]]=13,10, IF(Table1[[#This Row],[Point Value]]=20, 15,IF(Table1[[#This Row],[Point Value]]=40,40)))))))) -> 40 | G28: Tester
C29: UAT | E29: 13 | F29: =IF(Table1[[#This Row],[Point Value]]=1,1,IF(Table1[[#This Row],[Point Value]]=2,2,IF(Table1[[#This Row],[Point Value]]=3,3,IF(Table1[[#This Row],[Point Value]]=5,4, IF(Table1[[#This Row],[Point Value]]=8,5, IF(Table1[[#This Row],[Point Value]]=13,10, IF(Table1[[#This Row],[Point Value]]=20, 15,IF(Table1[[#This Row],[Point Value]]=40,40)))))))) -> 10 | G29: Tester
C30: PIV | E30: 2 | F30: =IF(Table1[[#This Row],[Point Value]]=1,1,IF(Table1[[#This Row],[Point Value]]=2,2,IF(Table1[[#This Row],[Point Value]]=3,3,IF(Table1[[#This Row],[Point Value]]=5,4, IF(Table1[[#This Row],[Point Value]]=8,5, IF(Table1[[#This Row],[Point Value]]=13,10, IF(Table1[[#This Row],[Point Value]]=20, 15,IF(Table1[[#This Row],[Point Value]]=40,40)))))))) -> 2 | G30: Tester
B31: DB Development | C31: DB Admin | E31: 13 | F31: =IF(Table1[[#This Row],[Point Value]]=1,1,IF(Table1[[#This Row],[Point Value]]=2,2,IF(Table1[[#This Row],[Point Value]]=3,3,IF(Table1[[#This Row],[Point Value]]=5,4, IF(Table1[[#This Row],[Point Value]]=8,5, IF(Table1[[#This Row],[Point Value]]=13,10, IF(Table1[[#This Row],[Point Value]]=20, 15,IF(Table1[[#This Row],[Point Value]]=40,40)))))))) -> 10 | G31: Backend DBA
C32: DB Development | E32: 13 | F32: =IF(Table1[[#This Row],[Point Value]]=1,1,IF(Table1[[#This Row],[Point Value]]=2,2,IF(Table1[[#This Row],[Point Value]]=3,3,IF(Table1[[#This Row],[Point Value]]=5,4, IF(Table1[[#This Row],[Point Value]]=8,5, IF(Table1[[#This Row],[Point Value]]=13,10, IF(Table1[[#This Row],[Point Value]]=20, 15,IF(Table1[[#This Row],[Point Value]]=40,40)))))))) -> 10 | G32: Backend Developer
C33: Azure Development | E33: 13 | F33: =IF(Table1[[#This Row],[Point Value]]=1,1,IF(Table1[[#This Row],[Point Value]]=2,2,IF(Table1[[#This Row],[Point Value]]=3,3,IF(Table1[[#This Row],[Point Value]]=5,4, IF(Table1[[#This Row],[Point Value]]=8,5, IF(Table1[[#This Row],[Point Value]]=13,10, IF(Table1[[#This Row],[Point Value]]=20, 15,IF(Table1[[#This Row],[Point Value]]=40,40)))))))) -> 10 | G33: Azure DevOps Developer
B34: DevSecOps Pipeline | C34: Create Project | E34: 1 | F34: =IF(Table1[[#This Row],[Point Value]]=1,1,IF(Table1[[#This Row],[Point Value]]=2,2,IF(Table1[[#This Row],[Point Value]]=3,3,IF(Table1[[#This Row],[Point Value]]=5,4, IF(Table1[[#This Row],[Point Value]]=8,5, IF(Table1[[#This Row],[Point Value]]=13,10, IF(Table1[[#This Row],[Point Value]]=20, 15,IF(Table1[[#This Row],[Point Value]]=40,40)))))))) -> 1 | G34: Azure DevOps Developer
C35: Create Azure Dashbaords | E35: 8 | F35: =IF(Table1[[#This Row],[Point Value]]=1,1,IF(Table1[[#This Row],[Point Value]]=2,2,IF(Table1[[#This Row],[Point Value]]=3,3,IF(Table1[[#This Row],[Point Value]]=5,4, IF(Table1[[#This Row],[Point Value]]=8,5, IF(Table1[[#This Row],[Point Value]]=13,10, IF(Table1[[#This Row],[Point Value]]=20, 15,IF(Table1[[#This Row],[Point Value]]=40,40)))))))) -> 5 | G35: Azure DevOps Developer
C36: Create Repo | E36: 1 | F36: =IF(Table1[[#This Row],[Point Value]]=1,1,IF(Table1[[#This Row],[Point Value]]=2,2,IF(Table1[[#This Row],[Point Value]]=3,3,IF(Table1[[#This Row],[Point Value]]=5,4, IF(Table1[[#This Row],[Point Value]]=8,5, IF(Table1[[#This Row],[Point Value]]=13,10, IF(Table1[[#This Row],[Point Value]]=20, 15,IF(Table1[[#This Row],[Point Value]]=40,40)))))))) -> 1 | G36: Azure DevOps Developer
C37: Create Artifacts | E37: 3 | F37: =IF(Table1[[#This Row],[Point Value]]=1,1,IF(Table1[[#This Row],[Point Value]]=2,2,IF(Table1[[#This Row],[Point Value]]=3,3,IF(Table1[[#This Row],[Point Value]]=5,4, IF(Table1[[#This Row],[Point Value]]=8,5, IF(Table1[[#This Row],[Point Value]]=13,10, IF(Table1[[#This Row],[Point Value]]=20, 15,IF(Table1[[#This Row],[Point Value]]=40,40)))))))) -> 3 | G37: Azure DevOps Developer
C38: Setup Pipeline | E38: 8 | F38: =IF(Table1[[#This Row],[Point Value]]=1,1,IF(Table1[[#This Row],[Point Value]]=2,2,IF(Table1[[#This Row],[Point Value]]=3,3,IF(Table1[[#This Row],[Point Value]]=5,4, IF(Table1[[#This Row],[Point Value]]=8,5, IF(Table1[[#This Row],[Point Value]]=13,10, IF(Table1[[#This Row],[Point Value]]=20, 15,IF(Table1[[#This Row],[Point Value]]=40,40)))))))) -> 5 | G38: Azure DevOps Developer
C39: Security Test Plans | E39: 8 | F39: =IF(Table1[[#This Row],[Point Value]]=1,1,IF(Table1[[#This Row],[Point Value]]=2,2,IF(Table1[[#This Row],[Point Value]]=3,3,IF(Table1[[#This Row],[Point Value]]=5,4, IF(Table1[[#This Row],[Point Value]]=8,5, IF(Table1[[#This Row],[Point Value]]=13,10, IF(Table1[[#This Row],[Point Value]]=20, 15,IF(Table1[[#This Row],[Point Value]]=40,40)))))))) -> 5 | G39: Azure DevOps Developer
B40: Project Management | C40: Scrum Master/PM | F40: 50 | G40: Project Manager
C41: BA | F41: 25 | G41: Business Analyst
C42: Tech Lead / App Architect/SA | F42: 60 | G42: Technical Architect

Sheet Resources and Effort
B1: Resources Required | T1: Effort
A2: App Name | B2: SDA | C2: SA | D2: PM | E2: BA | F2: Architect | G2: Tech Lead | H2: Dev1 | I2: Dev2 | J2: Mobile Lead | K2: Mobile Dev | L2: Test Lead | M2: Test Engineer | N2: DBA | O2: DB Developer | P2: UX | Q2: UI | R2: Cloud Architect | S2: DevOps Engineer | T2: Man Hours | U2: Man Days | V2: Man Months
A3: DI | B3: ü | C3: ü | D3: ü | E3: ü | F3: ü | G3: ü | H3: ü | I3: ü | J3: ý | K3: ý | L3: ü | M3: ü | N3: ü | O3: ü | P3: ü | Q3: ü | R3: ü | S3: ü | T3: 5520 | U3: 690 | V3: =U3/20 -> 34.5
A4: Survey | B4: ü | C4: ü | D4: ü | E4: ü | F4: ü | G4: ü | H4: ü | I4: ü | J4: ü | K4: ü | L4: ü | M4: ü | N4: ü | O4: ü | P4: ü | Q4: ü | R4: ü | S4: ü | T4: 5936 | U4: 742 | V4: 37.1
A5: CWT | B5: ü | C5: ü | D5: ü | E5: ü | F5: ü | G5: ü | H5: ü | I5: ü | J5: ý | K5: ý | L5: ü | M5: ü | N5: ü | O5: ü | P5: ü | Q5: ü | R5: ü | S5: ü | T5: 4976 | U5: 622 | V5: 31
A6: CAF | B6: ü | C6: ü | D6: ü | E6: ü | F6: ü | G6: ü | H6: ü | I6: ü | J6: ý | K6: ý | L6: ü | M6: ü | N6: ü | O6: ü | P6: ü | Q6: ü | R6: ü | S6: ü | T6: 12400 | U6: 1550 | V6: 78
A7: R&I | B7: ý | C7: ý | D7: ü | E7: ü | F7: ý | G7: ü | H7: ü | I7: ý | J7: ý | K7: ý | L7: ý | M7: ü | N7: ý | O7: ý | P7: ý | Q7: ý | R7: ý | S7: ý | T7: 680 | U7: =T7/8 -> 85 | V7: =T7/200 -> 3.4
A8: BBS | B8: ý | C8: ý | D8: ü | E8: ü | F8: ý | G8: ü | H8: ü | I8: ü | J8: ý | K8: ý | L8: ý | M8: ü | N8: ý | O8: ý | P8: ý | Q8: ý | R8: ý | S8: ý | T8: 992.0625 | U8: 90.125 | V8: =T8/200 -> 4.9603125
A9: Cadence | B9: ý | C9: ý | D9: ü | E9: ü | F9: ý | G9: ü | H9: ü | I9: ý | J9: ý | K9: ý | L9: ý | M9: ü | N9: ý | O9: ý | P9: ý | Q9: ý | R9: ý | S9: ý | T9: 1208 | U9: =T9/8 -> 151 | V9: =T9/200 -> 6.04
A12: App Name | B12: Man Hours | C12: Man Days | D12: Man Months
A13: DI | B13: 5520 | C13: 690 | D13: =C13/20 -> 34.5
A14: Survey | B14: 5936 | C14: 742 | D14: 37.1
A15: CWT | B15: 4976 | C15: 622 | D15: 31
A16: CAF | B16: 12400 | C16: 1550 | D16: 78
A17: R&I | B17: 921 | C17: 115.125 | D17: 5.75625
A18: BBS | B18: 1647 | C18: 205.875 | D18: 10.29375
A19: Cadence | B19: 2728 | C19: 341 | D19: 17.05
A20: Totals | B20: =SUM(B13:B19) -> 34128 | C20: =SUM(C13:C19) -> 4266 | D20: =SUM(D13:D19) -> 213.7

Sheet Complexity Summary
A1: App Name | B1: User Stories | C1: Tasks | D1: Sub Tasks | E1: Web Forms
A2: Digitalised Invoice (DI) | B2: 36 | C2: 60 | D2: 8 | E2: ='All apps Estimation Summary'!B23 -> 82
A3: Survey App (+Mobile) | B3: 16 | C3: 82 | D3: 44 | E3: 35
A4: Credit Application Form (CAF) | B4: 24 | C4: 95 | D4: 125 | E4: 120
A5: Certificate of Withholding Tax (CWT) | B5: 13 | C5: 49 | D5: 5 | E5: =Table9[[#Totals],[Web Forms]] -> 22
A6: BBS | B6: =BBS!C159 -> 24 | C6: =BBS!D159 -> 90 | D6: =BBS!E159 -> 68 | E6: =BBS!A159 -> 37
A7: Cadence | B7: =Cadence!C34 -> 15 | C7: =Cadence!D34 -> 27 | D7: =Cadence!E34 -> 18 | E7: =Cadence!A34 -> 23
A8: Risk & Insurance | B8: ='Risk & Insurance'!C59 -> 5 | C8: ='Risk & Insurance'!D59 -> 22 | D8: ='Risk & Insurance'!E59 -> 10 | E8: ='Risk & Insurance'!A59 -> 13

Sheet All apps Estimation Summary
A1: CCBPI Modernization Estimation | B1: Digitalised Invoice (DI) | E1: Survey App (+Mobile) | H1: Credit Application Form (CAF) | K1: Certificate of Withholding Tax (CWT) | N1: Risk & Insurance Portal | Q1: Cadence | T1: BBS
A2: Roles | B2: Effort In Hours | C2: Effotrt In Days | D2: Effort In Months | E2: Effort In Hours | F2: Effotrt In Days | G2: Effort In Months | H2: Effort In Hours | I2: Effotrt In Days | J2: Effort In Months | K2: Effort In Hours | L2: Effotrt In Days | M2: Effort In Months | N2: Effort In Hours | O2: Effotrt In Days | P2: Effort In Months | Q2: Effort In Hours | R2: Effotrt In Days | S2: Effort In Months | T2: Effort In Hours | U2: Effotrt In Days | V2: Effort In Months
A3: SDA | B3: =C3*8 -> 56 | C3: 7 | D3: =C3/20 -> 0.35 | E3: =F3*8 -> 56 | F3: 7 | G3: =F3/20 -> 0.35 | H3: =I3*8 -> 120 | I3: 15 | J3: =I3/20 -> 0.75 | K3: =L3*8 -> 56 | L3: 7 | M3: =L3/20 -> 0.35
A4: SA | B4: =C4*8 -> 56 | C4: 7 | D4: =C4/20 -> 0.35 | E4: =F4*8 -> 56 | F4: 7 | G4: =F4/20 -> 0.35 | H4: =I4*8 -> 120 | I4: 15 | J4: =I4/20 -> 0.75 | K4: =L4*8 -> 56 | L4: 7 | M4: =L4/20 -> 0.35
A5: PM | B5: =C5*8 -> 272 | C5: 34 | D5: =ROUND(C5/20, 0) -> 2 | E5: =F5*8 -> 336 | F5: 42 | G5: =ROUND(F5/20,0) -> 2 | H5: =I5*8 -> 712 | I5: 89 | J5: =ROUND(I5/20,0) -> 4 | K5: =L5*8 -> 256 | L5: 32 | M5: =ROUND(L5/20, 0) -> 2 | N5: 111 | O5: =N5/8 -> 13.875 | P5: =O5/20 -> 0.69375 | Q5: 183 | R5: =Q5/8 -> 22.875 | S5: =R5/20 -> 1.14375 | T5: 253 | U5: =T5/8 -> 31.625 | V5: =U5/20 -> 1.58125
A6: BA | B6: =C6*8 -> 272 | C6: 34 | D6: =ROUND(C6/20, 0) -> 2 | E6: =F6*8 -> 344 | F6: 43 | G6: =ROUND(F6/20,0) -> 2 | H6: =I6*8 -> 712 | I6: 89 | J6: =ROUND(I6/20,0) -> 4 | K6: =L6*8 -> 256 | L6: 32 | M6: =ROUND(L6/20, 0) -> 2 | N6: 69 | O6: =N6/8 -> 8.625 | P6: =O6/20 -> 0.43125 | Q6: 195 | R6: =Q6/8 -> 24.375 | S6: =R6/20 -> 1.21875 | T6: 255 | U6: =T6/8 -> 31.875 | V6: =U6/20 -> 1.59375
A7: Architect | B7: =C7*8 -> 256 | C7: 32 | D7: =ROUND(C7/20, 0) -> 2 | E7: =F7*8 -> 344 | F7: 43 | G7: =ROUND(F7/20,0) -> 2 | H7: =I7*8 -> 720 | I7: 90 | J7: =ROUND(I7/20,0) -> 5 | K7: =L7*8 -> 296 | L7: 37 | M7: =ROUND(L7/20, 0) -> 2
A8: Tech Lead | B8: =C8*8 -> 440 | C8: 55 | D8: =ROUND(C8/20, 0) -> 3 | E8: =F8*8 -> 448 | F8: 56 | G8: =ROUND(F8/20,0) -> 3 | H8: =I8*8 -> 1120 | I8: 140 | J8: =ROUND(I8/20,0) -> 7 | K8: =L8*8 -> 408 | L8: 51 | M8: =ROUND(L8/20, 0) -> 3
A9: Dev1 | B9: =C9*8 -> 720 | C9: 90 | D9: =ROUND(C9/20, 0) -> 5 | E9: =F9*8 -> 768 | F9: 96 | G9: =ROUND(F9/20,0) -> 5 | H9: =I9*8 -> 1704 | I9: 213 | J9: =ROUND(I9/20,0) -> 11 | K9: =L9*8 -> 648 | L9: 81 | M9: =ROUND(L9/20, 0) -> 4 | N9: 660 | O9: =N9/8 -> 82.5 | P9: =O9/20 -> 4.125 | Q9: 1020 | R9: =Q9/8 -> 127.5 | S9: =R9/20 -> 6.375 | T9: 1860 | U9: =T9/8 -> 232.5 | V9: =U9/20 -> 11.625
A10: Dev2 | B10: =C10*8 -> 720 | C10: 90 | D10: =ROUND(C10/20, 0) -> 5 | E10: =F10*8 -> 768 | F10: 96 | G10: =ROUND(F10/20,0) -> 5 | H10: =I10*8 -> 1704 | I10: 213 | J10: =ROUND(I10/20,0) -> 11 | K10: =L10*8 -> 648 | L10: 81 | M10: =ROUND(L10/20, 0) -> 4
A11: Test Lead | B11: =C11*8 -> 352 | C11: 44 | D11: =ROUND(C11/20, 0) -> 2 | E11: =F11*8 -> 352 | F11: 44 | G11: =ROUND(F11/20,0) -> 2 | H11: =I11*8 -> 752 | I11: 94 | J11: =ROUND(I11/20,0) -> 5 | K11: =L11*8 -> 312 | L11: 39 | M11: =ROUND(L11/20, 0) -> 2
A12: Test Engineer | B12: =C12*8 -> 536 | C12: 67 | D12: =ROUND(C12/20, 0) -> 3 | E12: =F12*8 -> 600 | F12: 75 | G12: =ROUND(F12/20,0) -> 4 | H12: =I12*8 -> 1328 | I12: 166 | J12: =ROUND(I12/20,0) -> 8 | K12: =L12*8 -> 520 | L12: 65 | M12: =ROUND(L12/20, 0) -> 3 | N12: 81 | O12: =N12/8 -> 10.125 | P12: =O12/20 -> 0.50625 | Q12: 249 | R12: =Q12/8 -> 31.125 | S12: =R12/20 -> 1.55625 | T12: 360 | U12: =T12/8 -> 45 | V12: =U12/20 -> 2.25
A13: DBA | B13: =C13*8 -> 248 | C13: 31 | D13: =ROUND(C13/20, 0) -> 2 | E13: =F13*8 -> 248 | F13: 31 | G13: =ROUND(F13/20,0) -> 2 | H13: =I13*8 -> 632 | I13: 79 | J13: =ROUND(I13/20,0) -> 4 | K13: =L13*8 -> 208 | L13: 26 | M13: =ROUND(L13/20, 0) -> 1
A14: DB Developer | B14: =C14*8 -> 432 | C14: 54 | D14: =ROUND(C14/20, 0) -> 3 | E14: =F14*8 -> 456 | F14: 57 | G14: =ROUND(F14/20,0) -> 3 | H14: =I14*8 -> 1024 | I14: 128 | J14: =ROUND(I14/20,0) -> 6 | K14: =L14*8 -> 408 | L14: 51 | M14: =ROUND(L14/20, 0) -> 3
A15: UX | B15: =C15*8 -> 432 | C15: 54 | D15: =ROUND(C15/20, 0) -> 3 | E15: =F15*8 -> 424 | F15: 53 | G15: =ROUND(F15/20,0) -> 3 | H15: =I15*8 -> 768 | I15: 96 | J15: =ROUND(I15/20,0) -> 5 | K15: =L15*8 -> 288 | L15: 36 | M15: =ROUND(L15/20, 0) -> 2
A16: UI | B16: =C16*8 -> 520 | C16: 65 | D16: =ROUND(C16/20, 0) -> 3 | E16: =F16*8 -> 528 | F16: 66 | G16: =ROUND(F16/20,0) -> 3 | H16: =I16*8 -> 904 | I16: 113 | J16: =ROUND(I16/20,0) -> 6 | K16: =L16*8 -> 408 | L16: 51 | M16: =ROUND(L16/20, 0) -> 3
A17: Cloud Architect | B17: =C17*8 -> 160 | C17: 20 | D17: =ROUND(C17/20, 0) -> 1 | E17: =F17*8 -> 160 | F17: 20 | G17: =ROUND(F17/20,0) -> 1 | H17: =I17*8 -> 160 | I17: 20 | J17: =ROUND(I17/20,0) -> 1 | K17: =L17*8 -> 160 | L17: 20 | M17: =ROUND(L17/20, 0) -> 1
A18: DevOps Engineer | B18: =C18*8 -> 160 | C18: 20 | D18: =ROUND(C18/20, 0) -> 1 | E18: =F18*8 -> 160 | F18: 20 | G18: =ROUND(F18/20,0) -> 1 | H18: =I18*8 -> 160 | I18: 20 | J18: =ROUND(I18/20,0) -> 1 | K18: =L18*8 -> 160 | L18: 20 | M18: =ROUND(L18/20, 0) -> 1
A19: Totals | B19: =SUM(B5:B18) -> 5520 | C19: =SUM(C5:C18) -> 690 | D19: =SUM(D5:D18) -> 37 | E19: =SUM(E5:E18) -> 5936 | F19: =SUM(F5:F18) -> 742 | G19: =F19/20 -> 37.1 | H19: =SUM(H5:H18) -> 12400 | I19: =SUM(I5:I18) -> 1550 | J19: =ROUND(I19/20,0) -> 78 | K19: =SUM(K5:K18) -> 4976 | L19: =SUM(L5:L18) -> 622 | M19: =SUM(M5:M18) -> 33 | N19: =SUM(N5:N18) -> 921 | O19: =SUM(O5:O18) -> 115.125 | P19: =SUM(P5:P18) -> 5.75625 | Q19: =SUM(Q5:Q18) -> 1647 | R19: =SUM(R5:R18) -> 205.875 | ... V19: =SUM(V5:V18) -> 17.05
A20: User Stories | B20: ='Digitalized Invoice Effort'!B107+'Digitalized Invoice Effort'!A107 -> 36 | E20: ='Survey App Effort'!B148 -> 16 | H20: ='CAF Effort'!B251 -> 24 | K20: ='CWT Effort'!B66 -> 13 | N20: 5 | O20: 5 | P20: 5 | Q20: 15 | R20: 15 | S20: 15 | T20: 24
A21: Tasks | B21: ='Digitalized Invoice Effort'!C107 -> 60 | E21: ='Survey App Effort'!C148 -> 82 | H21: ='CAF Effort'!C251 -> 95 | K21: ='CWT Effort'!C66 -> 49 | N21: 22 | O21: 22 | P21: 22 | Q21: 27 | R21: 27 | S21: 27 | T21: 90
A22: Sub Tasks | B22: ='Digitalized Invoice Effort'!D107 -> 8 | E22: ='Survey App Effort'!D148 -> 44 | H22: ='CAF Effort'!D251 -> 125 | K22: ='Digitalized Invoice Effort'!A107 -> 5 | N22: 10 | O22: 10 | P22: 10 | Q22: 18 | R22: 18 | S22: 18 | T22: 68
A23: Web Forms | B23: ='Digitalized Invoice Effort'!E107 -> 82 | E23: ='Survey App Effort'!E148 -> 54 | H23: 120 | K23: ='CWT Effort'!E66 -> 22 | N23: 13 | O23: 13 | P23: 13 | Q23: 23 | R23: 23 | S23: 23 | T23: 37

Sheet Summary_old
A1: APP | B1: PM | C1: BA | D1: Architect | E1: Tech Lead | F1: Dev1 | G1: Dev2 | H1: Test Lead | I1: Test Engineer | J1: DBA | K1: DB Developer | L1: UX | M1: UI | N1: Cloud Architect | O1: DevOps Engineer | P1: App Effort (In Days | Q1: Months | R1: Hours
A2: Digitalised Invoice | B2: 34 | C2: 34 | D2: 32 | E2: 55 | F2: 90 | G2: 90 | H2: 44 | I2: 67 | J2: 31 | K2: 54 | L2: 54 | M2: 65 | N2: 20 | O2: 20 | P2: =SUM(Table712[[#This Row],[PM]:[DevOps Engineer]]) -> 690 | Q2: =Table712[[#This Row],[App Effort (In Days]]/22 -> 31.363636 | R2: =Table712[[#This Row],[App Effort (In Days]]*8 -> 5520
A3: Survey Application | B3: 42 | C3: 43 | D3: 43 | E3: 56 | F3: 96 | G3: 96 | H3: 44 | I3: 75 | J3: 31 | K3: 57 | L3: 53 | M3: 66 | N3: 20 | O3: 20 | P3: =SUM(Table712[[#This Row],[PM]:[DevOps Engineer]]) -> 742 | Q3: =Table712[[#This Row],[App Effort (In Days]]/22 -> 33.727273 | R3: =Table712[[#This Row],[App Effort (In Days]]*8 -> 5936
A4: CWT | B4: 32 | C4: 32 | D4: 37 | E4: 51 | F4: 81 | G4: 81 | H4: 39 | I4: 65 | J4: 26 | K4: 51 | L4: 36 | M4: 51 | N4: 20 | O4: 20 | P4: =SUM(Table712[[#This Row],[PM]:[DevOps Engineer]]) -> 622 | Q4: =Table712[[#This Row],[App Effort (In Days]]/22 -> 28.272727 | R4: =Table712[[#This Row],[App Effort (In Days]]*8 -> 4976
A5: CAF | B5: ='CAF Effort'!E250 -> 89 | C5: ='CAF Effort'!F250 -> 89 | D5: ='CAF Effort'!G250 -> 90 | E5: ='CAF Effort'!H250 -> 140 | F5: ='CAF Effort'!I250 -> 213 | G5: ='CAF Effort'!J250 -> 213 | H5: ='CAF Effort'!K250 -> 94 | I5: ='CAF Effort'!L250 -> 166 | ... M5: ='CAF Effort'!P250 -> 113 | N5: 20 | O5: 20 | P5: =SUM(Table712[[#This Row],[PM]:[DevOps Engineer]]) -> 1550 | Q5: =Table712[[#This Row],[App Effort (In Days]]/22 -> 70.454545 | R5: =Table712[[#This Row],[App Effort (In Days]]*8 -> 12400
A6: Total | B6: =SUM(B2:B5) -> 197 | C6: =SUM(C2:C5) -> 198 | D6: =SUM(D2:D5) -> 202 | E6: =SUM(E2:E5) -> 302 | F6: =SUM(F2:F5) -> 480 | G6: =SUM(G2:G5) -> 480 | H6: =SUM(H2:H5) -> 221 | I6: =SUM(I2:I5) -> 373 | ... O6: =SUM(O2:O5) -> 80 | P6: =SUM(Table712[[#This Row],[PM]:[DevOps Engineer]]) -> 3604 | Q6: =Table712[[#This Row],[App Effort (In Days]]/22 -> 163.81818 | R6: =Table712[[#This Row],[App Effort (In Days]]*8 -> 28832
A7: Exact Month | B7: =B6/20 -> 9.85 | C7: =C6/20 -> 9.9 | D7: =D6/20 -> 10.1 | E7: =E6/20 -> 15.1 | F7: =F6/20 -> 24 | G7: =G6/20 -> 24 | H7: =H6/20 -> 11.05 | I7: =I6/20 -> 18.65 | ... P7: =P6/20 -> 180.2
A8: Rounded - Head Count | B8: 2 | C8: 2 | D8: 2 | E8: 3 | F8: 4 | G8: 4 | H8: 2 | I8: 3 | J8: 1 | K8: 3 | L8: 2 | M8: 3 | N8: 1 | O8: 1
A12: CAF Values | B12: 89 | C12: 89 | D12: 90 | E12: 140 | F12: 213 | G12: 213 | H12: 94 | I12: 166 | J12: 79 | K12: 128 | L12: 96 | M12: 113 | N12: 20 | O12: 20

Sheet Power Apps Estimation
A2: Risk & Insurance Portal | B2: Access Creation & Initiation | C2: Requirements Gathering, User Story Creation, Sprint Backlogs, Acceptance Criteria | D2: Build & Test (Web & Mobile Applications) | M2: Reworks & UAT | N2: Go live & Hypercare | O2: Total Effort
B3: Month 1 - June | F3: Month 2 - July | J3: Month 3 - August
B4: Sprint 1 | D4: Sprint 2 | F4: Sprint 3 | H4: Sprint 4 | J4: Sprint 5 | L4: Sprint 6 | O4: =SUM(O7:O13) -> 921
A5: Weeks | B5: W1 | C5: W2 | D5: W3 | E5: W4 | F5: W5 | G5: W6 | H5: W7 | I5: W8 | J5: W9 | K5: W10 | L5: W11 | M5: W12 | N5: W13
A6: Developers | C6: 2 | D6: 2 | E6: 2 | F6: 2 | G6: 2 | H6: 2 | I6: 2 | J6: 2 | K6: 2 | L6: 2 | M6: 1 | N6: 1
A7: Efforts | B7: =B6*5*6 -> 0 | C7: =C6*5*6 -> 60 | D7: =D6*5*6 -> 60 | E7: =E6*5*6 -> 60 | F7: =F6*5*6 -> 60 | G7: =G6*5*6 -> 60 | H7: =H6*5*6 -> 60 | I7: =I6*5*6 -> 60 | ... N7: =N6*5*6 -> 30 | O7: =SUM(B7:N7) -> 660
A8: QA | F8: 0.3 | G8: 0.3 | H8: 0.3 | I8: 0.3 | J8: 0.3 | K8: 0.3 | L8: 0.3 | M8: 0.3 | N8: 0.3
A9: Effort | B9: =B8*6*5 -> 0 | C9: =C8*6*5 -> 0 | D9: =D8*6*5 -> 0 | E9: =E8*6*5 -> 0 | F9: =F8*6*5 -> 9 | G9: =G8*6*5 -> 9 | H9: =H8*6*5 -> 9 | I9: =I8*6*5 -> 9 | ... N9: =N8*6*5 -> 9 | O9: =SUM(B9:N9) -> 81
A10: BA | B10: 0.3 | C10: 0.3 | D10: 0.3 | E10: 0.3 | F10: 0.1 | G10: 0.1 | H10: 0.1 | I10: 0.1 | J10: 0.1 | K10: 0.1 | L10: 0.1 | M10: 0.1 | N10: 0.3
A11: Effort | B11: =B10*5*6 -> 9 | C11: =C10*5*6 -> 9 | D11: =D10*5*6 -> 9 | E11: =E10*5*6 -> 9 | F11: =F10*5*6 -> 3 | G11: =G10*5*6 -> 3 | H11: =H10*5*6 -> 3 | I11: =I10*5*6 -> 3 | ... N11: =N10*5*6 -> 9 | O11: =SUM(B11:N11) -> 69
A12: PM | B12: 0.3 | C12: 0.3 | D12: 0.3 | E12: 0.3 | F12: 0.3 | G12: 0.3 | H12: 0.3 | I12: 0.3 | J12: 0.3 | K12: 0.3 | L12: 0.3 | M12: 0.3 | N12: 0.1
A13: Effort | B13: =B12*5*6 -> 9 | C13: =C12*5*6 -> 9 | D13: =D12*5*6 -> 9 | E13: =E12*5*6 -> 9 | F13: =F12*5*6 -> 9 | G13: =G12*5*6 -> 9 | H13: =H12*5*6 -> 9 | I13: =I12*5*6 -> 9 | ... N13: =N12*5*6 -> 3 | O13: =SUM(B13:N13) -> 111
A17: Cadence | B17: Access Creation & Initiation | C17: Requirements Gathering, User Story Creation, Sprint Backlogs, Acceptance Criteria | D17: Build & Test (Web & Mobile Applications) | M17: Reworks & UAT | N17: Go live & Hypercare | O17: Total Effort
B18: Month 1 - June | F18: Month 2 - July | J18: Month 3 - August
B19: Sprint 1 | D19: Sprint 2 | F19: Sprint 3 | H19: Sprint 4 | J19: Sprint 5 | L19: Sprint 6 | O19: =SUM(O22:O28) -> 1647
A20: Weeks | B20: W1 | C20: W2 | D20: W3 | E20: W4 | F20: W5 | G20: W6 | H20: W7 | I20: W8 | J20: W9 | K20: W10 | L20: W11 | M20: W12 | N20: W13
A21: Developers | C21: 3 | D21: 3 | E21: 3 | F21: 3 | G21: 3 | H21: 3 | I21: 3 | J21: 3 | K21: 3 | L21: 3 | M21: 3 | N21: 1
A22: Efforts | B22: =B21*5*6 -> 0 | C22: =C21*5*6 -> 90 | D22: =D21*5*6 -> 90 | E22: =E21*5*6 -> 90 | F22: =F21*5*6 -> 90 | G22: =G21*5*6 -> 90 | H22: =H21*5*6 -> 90 | I22: =I21*5*6 -> 90 | ... N22: =N21*5*6 -> 30 | O22: =SUM(B22:N22) -> 1020
A23: QA | F23: 1 | G23: 1 | H23: 1 | I23: 1 | J23: 1 | K23: 1 | L23: 1 | M23: 1 | N23: 0.3
A24: Effort | B24: =B23*6*5 -> 0 | C24: =C23*6*5 -> 0 | D24: =D23*6*5 -> 0 | E24: =E23*6*5 -> 0 | F24: =F23*6*5 -> 30 | G24: =G23*6*5 -> 30 | H24: =H23*6*5 -> 30 | I24: =I23*6*5 -> 30 | ... N24: =N23*6*5 -> 9 | O24: =SUM(B24:N24) -> 249
A25: BA | B25: 0.5 | C25: 0.5 | D25: 0.5 | E25: 0.5 | F25: 0.5 | G25: 0.5 | H25: 0.5 | I25: 0.5 | J25: 0.5 | K25: 0.5 | L25: 0.5 | M25: 0.5 | N25: 0.5
A26: Effort | B26: =B25*5*6 -> 15 | C26: =C25*5*6 -> 15 | D26: =D25*5*6 -> 15 | E26: =E25*5*6 -> 15 | F26: =F25*5*6 -> 15 | G26: =G25*5*6 -> 15 | H26: =H25*5*6 -> 15 | I26: =I25*5*6 -> 15 | ... N26: =N25*5*6 -> 15 | O26: =SUM(B26:N26) -> 195
A27: PM | B27: 0.5 | C27: 0.5 | D27: 0.5 | E27: 0.5 | F27: 0.5 | G27: 0.5 | H27: 0.5 | I27: 0.5 | J27: 0.5 | K27: 0.5 | L27: 0.5 | M27: 0.5 | N27: 0.1
A28: Effort | B28: =B27*5*6 -> 15 | C28: =C27*5*6 -> 15 | D28: =D27*5*6 -> 15 | E28: =E27*5*6 -> 15 | F28: =F27*5*6 -> 15 | G28: =G27*5*6 -> 15 | H28: =H27*5*6 -> 15 | I28: =I27*5*6 -> 15 | ... N28: =N27*5*6 -> 3 | O28: =SUM(B28:N28) -> 183
A32: BBS | B32: Access Creation & Initiation | C32: Requirements Gathering, User Story Creation, Sprint Backlogs, Acceptance Criteria | D32: Build & Test (Web & Mobile Applications) | M32: Reworks & UAT | R32: Go live & Hypercare | S32: Total Effort
B33: Month 1 - June | F33: Month 2 - July | J33: Month 3 - August | N33: Month 4 - September
B34: Sprint 1 | D34: Sprint 2 | F34: Sprint 3 | H34: Sprint 4 | J34: Sprint 5 | L34: Sprint 6 | N34: Sprint 7 | P34: Sprint 8 | S34: =SUM(S37:S43) -> 2727
A35: Weeks | B35: W1 | C35: W2 | D35: W3 | E35: W4 | F35: W5 | G35: W6 | H35: W7 | I35: W8 | J35: W9 | K35: W10 | L35: W11 | M35: W12 | N35: W13 | O35: W14 | P35: W15 | Q35: W16 | R35: W17
A36: Developers | C36: 4 | D36: 4 | E36: 4 | F36: 4 | G36: 4 | H36: 4 | I36: 4 | J36: 4 | K36: 4 | L36: 4 | M36: 4 | N36: 4 | O36: 4 | P36: 4 | Q36: 4 | R36: 2
A37: Efforts | B37: =B36*5*6 -> 0 | C37: =C36*5*6 -> 120 | D37: =D36*5*6 -> 120 | E37: =E36*5*6 -> 120 | F37: =F36*5*6 -> 120 | G37: =G36*5*6 -> 120 | H37: =H36*5*6 -> 120 | I37: =I36*5*6 -> 120 | ... R37: =R36*5*6 -> 60 | S37: =SUM(B37:R37) -> 1860
A38: QA | F38: 1 | G38: 1 | H38: 1 | I38: 1 | J38: 1 | K38: 1 | L38: 1 | M38: 1 | N38: 1 | O38: 1 | P38: 1 | Q38: 1 | R38: 0.3
A39: Effort | B39: =B38*6*5 -> 0 | C39: =C38*6*5 -> 0 | D39: =D38*6*5 -> 0 | E39: =E38*6*5 -> 0 | F39: =F38*6*5 -> 30 | G39: =G38*6*5 -> 30 | H39: =H38*6*5 -> 30 | I39: =I38*6*5 -> 30 | ... R39: =R38*6*5 -> 9 | S39: =SUM(B39:R39) -> 369
A40: BA | B40: 0.5 | C40: 0.5 | D40: 0.5 | E40: 0.5 | F40: 0.5 | G40: 0.5 | H40: 0.5 | I40: 0.5 | J40: 0.5 | K40: 0.5 | L40: 0.5 | M40: 0.5 | N40: 0.5 | O40: 0.5 | P40: 0.5 | Q40: 0.5 | R40: 0.5
A41: Effort | B41: =B40*5*6 -> 15 | C41: =C40*5*6 -> 15 | D41: =D40*5*6 -> 15 | E41: =E40*5*6 -> 15 | F41: =F40*5*6 -> 15 | G41: =G40*5*6 -> 15 | H41: =H40*5*6 -> 15 | I41: =I40*5*6 -> 15 | ... R41: =R40*5*6 -> 15 | S41: =SUM(B41:R41) -> 255
A42: PM | B42: 0.5 | C42: 0.5 | D42: 0.5 | E42: 0.5 | F42: 0.5 | G42: 0.5 | H42: 0.5 | I42: 0.5 | J42: 0.5 | K42: 0.5 | L42: 0.5 | M42: 0.5 | N42: 0.5 | O42: 0.5 | P42: 0.5 | Q42: 0.5 | R42: 0.1
A43: Effort | B43: =B42*5*6 -> 15 | C43: =C42*5*6 -> 15 | D43: =D42*5*6 -> 15 | E43: =E42*5*6 -> 15 | F43: =F42*5*6 -> 15 | G43: =G42*5*6 -> 15 | H43: =H42*5*6 -> 15 | I43: =I42*5*6 -> 15 | ... R43: =R42*5*6 -> 3 | S43: =SUM(B43:R43) -> 243
A47: Since in Power Apps, developers will not be able to publish at the same time, hence the developers needs to be considered in different time zones or working hours, with overlapping hours
A48: The timeline and estimation is entirely based on the captured features. Any change in the Scope will have to change the timeline.

Sheet Resource Loading
A1: Head Count | B1: Role | C1: Monthly Loading | D1: Hourly Loading | E1: FNT 1 | F1: FNT 2 | G1: FNT 3 | H1: FNT 4 | I1: FNT 5 | J1: FNT 6 | K1: FNT 7 | L1: FNT 8 | M1: FNT 9 | N1: FNT 10 | O1: FNT 11 | P1: FNT 12 | Q1: FNT 13 | R1: FNT 14 | S1: FNT 15 | T1: FNT 16 | U1: FNT 17 | V1: FNT 18 | W1: FNT 19 | X1: FNT 20
A2: 0.66666667 | B2: Project Manager | C2: 9 | D2: 5.33
A3: 1 | B3: Senior BA | C3: 8 | D3: 8
A4: 1 | B4: Presales Solution Architect | C4: 3 | D4: 6
A5: 1 | B5: Senior Delivery Manager | C5: 2 | D5: 5.33
A6: 0.66666667 | B6: Technical Architect | C6: 9 | D6: 5.33
A7: 1 | B7: .Net Technical Lead | C7: 8 | D7: 8
A8: 1 | B8: Front End Technical Lead | C8: 8 | D8: 8
A9: 2 | B9: Senior .Net Developer | C9: 9 | D9: 16
A10: 1 | B10: Junior .Net Developer | C10: 9 | D10: 8
A11: 0.25 | B11: Database Admin / Architect | C11: 7 | D11: 2
A12: 1 | B12: SQL Developer | C12: 7 | D12: 8
A13: 1 | B13: Senior SQL Developer | C13: 7 | D13: 8
... A23: 1 | B23: Senior Mobile Developer | C23: 6 | D23: 8

Sheet BBS
A1: From Name | B1: EPIC | C1: User Story | D1: Task | E1: Sub Task | F1: PM | G1: BA | H1: Architect | I1: Tech Lead | J1: Dev1 | K1: Dev2 | L1: QA Tester | M1: Test Engineer | N1: DBA | O1: DB Developer | P1: UX | Q1: UI
B2: 1. Behavior Based Safety Application
B3: 35+ | C3: New Site | D3: Create Site | F3: 1 | G3: 1 | I3: 1 | J3: 1 | K3: 1
D4: Create Groups and Permissions | J4: 1 | K4: 1
D5: Create Table structure to map all the tables | J5: 6 | K5: 6
D6: Create Lists in Sharepoint | J6: 4 | K6: 4
D7: Create Views for the list | J7: 2 | K7: 2
B9: PowerApps
A10: Login Screen | C10: Login Screen | D10: Create New Screen with login Button. | F10: 1 | G10: 1 | I10: 1 | J10: 3 | K10: 3 | L10: 3
A13: Dashborad | C13: Dashborad | D13: Create new sceen with UI Navigation | F13: 1 | G13: 1 | I13: 1 | J13: 1 | K13: 1 | L13: 3
D14: MU Coke BBS Compliance per site bar graph | E14: Power BI Report | J14: 5 | K14: 5
D15: MU Average BBS Compliance per Calendar Period line graph. | E15: Power BI Report | J15: 5 | K15: 5
D16: Banner with Notification message showing the pending Approvals | J16: 2.5 | K16: 2.5
D17: Search and Filters | J17: 2 | K17: 2
A19: RCA Home | C19: RCA Home | D19: Create new sceen with UI Navigation (Header,home,Back,Menu) | F19: 1 | G19: 1 | I19: 1 | J19: 2 | K19: 2 | L19: 3
D20: Display all the Root Cause Analysis submitted for Approval | J20: 1 | K20: 2
D21: RCA displays table of Date Period, Plant, perfomed by, Location, Status and action | J21: 2 | K21: 2
D22: Sorting functions for each soloumns | J22: 1.5 | K22: 1.5
A24: Perform RCA | C24: Perform RCA | D24: Create new sceen with UI Navigation (Header,home,Back,Menu) | F24: 1 | G24: 1 | I24: 1 | J24: 2 | K24: 2 | L24: 3
D25: View RCA details | J25: 2 | K25: 2
D26: Approve/ Reject buttons | E26: By clicking on approve an Approve Confirmation pop up message will appear. Click Approve to proceed or click Cancel and close icon will dismiss the current screen display. | J26: 2 | K26: 2
D27: Display Notification on Approve/reject | E27: If RCA submitted was approved “RCA submitted successfully approved.” and if rejwected “RCA submitted successfully Rejected" | J27: 1.5 | K27: 1.5
C29: Reports | D29: Contains all reports for below modules.
A30: Observation Report | D30: Observation Report | E30: Create new sceen with UI Navigation (Header,home,Back,Menu)Display Table listing details of Region, Sites, Observers, Date Observed, Area Observed, Task Observed. Each column listing can be sorted using the sorting icon beside each table column title Filter search and clear function Export report Icon | F30: 1 | G30: 1 | I30: 1 | J30: 8 | K30: 8 | L30: 2
A31: RCA Report | D31: RCA Report | E31: Create new sceen with UI Navigation (Header,home,Back,Menu) ,Display Table listing details ofof Date Period, Site, Performed by, location and Status. Each column listing can be sorted using the sorting icon beside each table column title Filter search and clear function Export report Icon | F31: 1 | G31: 1 | I31: 1 | J31: 8 | K31: 8 | L31: 2
A32: Effectiveness Report | D32: Effectiveness Report | E32: Create new sceen with UI Navigation (Header,home,Back,Menu), Display Table listing details of Period, Sites, Region, Critical Behaviour, Target Number of Answers, Actual Number of Answers, YES/NO/NA count, % Safe Behaviour and % Unsafe Behaviour. Each column listing can be sorted using the sorting icon beside each table column title Filter search and clear function Export report Icon | F32: 1 | G32: 1 | I32: 1 | J32: 8 | K32: 8 | L32: 2
A33: Observation Compliance Report | D33: Observation Compliance Report | E33: Create new sceen with UI Navigation (Header,home,Back,Menu), Display Table listing details of Period, Site, Region, Critical Behavior, Target Number of Answers, Actual Number of Answers, YES/NO/NA count, % Safe Behavior and % Unsafe Behavior. Each column listing can be sorted using the sorting icon beside each table column title. Filter search and clear function Export report Icon | F33: 1 | G33: 1 | I33: 1 | J33: 8 | K33: 8 | L33: 2
A34: BBS Compliance Report | D34: BBS Compliance Report | E34: Create new sceen with UI Navigation (Header,home,Back,Menu),Display Table listing details of Region, Plant, Period, Observation Compliance, % Observation, Unsafe Behavior, % Reduction, % Effectiveness, BBS Compliance for the Period and YTD BBS Compliance. Each column listing can be sorted using the sorting icon beside each table column title Filter search and clear function Export report Icon | F34: 1 | G34: 1 | I34: 1 | J34: 8 | K34: 8 | L34: 2
A36: Admin Screen | C36: Admin Site-Maintaince | D36: Admin Site contains below sub-tab | J36: 3 | K36: 3 | L36: 1.5
A37: Questions | D37: Questions | E37: Create new sceen with UI Navigation (Header,home,Back,Menu) ,Display List of Questions Edit/Deactive question Add new question | F37: 1 | G37: 1 | I37: 1 | J37: 4 | K37: 4 | L37: 1.5
A38: 445 Calendar | D38: 445 Calendar | E38: Create new sceen with UI Navigation (Header,home,Back,Menu), Display List Year, Period, Week, Start Date, and End date. Table be filtered by period and sorted per column. Download/Upload button to Download/Upload calendar | F38: 1 | G38: 1 | I38: 1 | J38: 4 | K38: 4 | L38: 2
A39: Target Definition | D39: Target Definition | E39: Create new sceen with UI Navigation (Header,home,Back,Menu), displays Year, National BBS Compliance Target (%), Weekly Observation Target per user, Weekly Observation Target effectivity date and Action. Table be filtered by period and sorted per column. Add New Target, Edit target | F39: 1 | G39: 1 | I39: 1 | J39: 5 | K39: 5 | L39: 2
A40: User Maintenance | C40: (Can be done for roles is sharepoint) | D40: User Maintenance | E40: Create new sceen with UI Navigation (Header,home,Back,Menu), Table listing displays Name, Email Address, Site, User Role, Date Added, Last Access, Active and Action. Filter and sort by columns. Add New User, edit/delete user role. Activate or deactivate users. | F40: 1 | G40: 1 | I40: 1 | J40: 5 | K40: 5 | L40: 2
A41: User Activation History | C41: (Can be done for roles is sharepoint) | D41: User Activation History | E41: Table listing displays User, Is Active Status, Site, User Role, Created Date, Date Added. Sort and filter by columns. Edit history | F41: 1 | G41: 1 | I41: 1 | J41: 4 | K41: 4 | L41: 2
A42: Unit Maintenance | D42: Unit Maintenance | E42: Create new sceen with UI Navigation (Header,home,Back,Menu), Table listing displays Name of Unit, Date Added, Active Status and Action. Filter and search. Add new Unit, Edit unit | F42: 1 | G42: 1 | I42: 1 | J42: 5 | K42: 5 | L42: 2
A43: Unit Detail Maintenance | D43: Unit Detail Maintenance | E43: Create new sceen with UI Navigation (Header,home,Back,Menu), 3 sub Units-Commercial unit, Logistic unit and Manufacturing Unit. For each unit Filter and search. Add new Unit, Edit unit | F43: 1 | G43: 1 | I43: 1 | J43: 5 | K43: 5 | L43: 2
B44: Power Automate flows | C44: Email Notification | D44: Create a power automate flow for email notifications | J44: 4 | K44: 4 | L44: 2
C45: Export to excel | D45: create power automate flow to export the gallery etails | J45: 4 | K45: 4 | L45: 2
B47: 2. Driver - Behavior Based Safety Application
B48: Sharepoint | C48: New Site | D48: Create Site | F48: 1 | G48: 1 | I48: 1 | J48: 1 | K48: 1
D49: Create Groups and Permissions | J49: 1 | K49: 1
D50: Create Table structure to map all the tables | J50: 6 | K50: 6
D51: Create Lists in Sharepoint | J51: 4 | K51: 4
D52: Create Views for the list | J52: 2 | K52: 2
A54: Dashboard screen | B54: PowerApps | C54: Dashboard | D54: Create new sceen with UI Navigation | F54: 1 | G54: 1 | I54: 1 | J54: 2 | K54: 2 | L54: 2.5
D55: Submission per site bar graph | E55: Power BI Report | J55: 4.5 | K55: 4.5
D56: Search and Filters | J56: 1.5 | K56: 1.5
D57: Banner with Notification message | J57: 2 | K57: 2
A59: Reports Home | C59: Reports Tab | D59: Create new Screen UI for three categories (Observations, Effectiveness and Observation Compliance) | F59: 1 | G59: 1 | I59: 1 | J59: 3 | K59: 3 | L59: 2
D60: Create search and filters | J60: 1 | K60: 1 | L60: 1
A61: Observation Report | D61: Observation Report | E61: Create a New UI navigation gallery in Reports Screen | F61: 1 | G61: 1 | I61: 1 | J61: 3 | K61: 3
E62: Create a button to download excel of the current report which is displayed in the gallery | J62: 2 | K62: 2
E63: The gallery contains following columns (Region, Site, Reviewer, Date Reviewed and Driver) | J63: 3 | K63: 3
A64: Effectiveness Report | D64: Effectiveness Report | E64: Create a New UI navigation gallery in Reports Screen | F64: 1 | G64: 1 | I64: 1 | J64: 3 | K64: 3 | L64: 2
E65: Create a button to download excel of the current report which is displayed in the gallery | J65: 2 | K65: 2
E66: The gallery contains following columns (Period, Site, Region, Critical Behavior, Target Number of Answers, Actual Number of Answers, YES/NO/NA count, % Safe Behavior and % Unsafe Behavior) | J66: 3 | K66: 3 | L66: 2
A67: Observation Compliance Report | D67: Observation Compliance Report | E67: Create a New UI navigation gallery in Reports Screen | F67: 1 | G67: 1 | I67: 1 | J67: 3 | K67: 3 | L67: 2
E68: Create a button to download excel of the current report which is displayed in the gallery | J68: 2 | K68: 2
E69: The gallery contains following columns (Period, Site, Region, Reviewer Name, Target Compliance, Observation Compliance, Target Number of Answers, Actual Number of Answers, YES/NO/NA count, % Safe Behavior and % Unsafe Behavior. ) | J69: 4 | K69: 4
A71: Admin Screen | C71: Admin Site | D71: Create a dropdown menu containing(Admin site,Questions,Driver and Target Definition) | F71: 1 | G71: 1 | I71: 1 | J71: 3 | K71: 3 | L71: 2
A73: Question Option | D73: Question Option | E73: Create New navigation And UI with a Gallery | J73: 3 | K73: 3 | L73: 2
E74: Create a Button to Add Questions | J74: 1 | K74: 1 | L74: 2
E75: Create a Active Button and a Action button in the gallery | J75: 1 | K75: 1
E76: Create a Pop up onclick on of add question | J76: 1 | K76: 1
E77: Create a text box inside the popupand a save button to save the edited/new question | J77: 1 | K77: 1
A79: Driver List | D79: Driver List | F79: 1 | G79: 1 | I79: 1 | L79: 2.5
E80: Create a Button to Add Driver | J80: 2 | K80: 2
E81: Create a Active Button and a Action button in the gallery | J81: 2 | K81: 2
E82: Create a Pop up onclick on of add Driver | J82: 2 | K82: 2
E83: Create a text box for last name, first name, middle name, dropdown for region and dropdown for site and a save button to save the edited/new driver | J83: 2 | K83: 2
E84: Create a download driver template option whhere an excel will be downloaded containing the template | J84: 2 | K84: 2
E85: Create a Bulk upload button which will use the same template file as an input for bulk upload of Driver | J85: 2 | K85: 2
E86: Create a popup for this Bulk upload and create a attachment option to place the template file and Create a upload button | J86: 2 | K86: 2
A88: Target Definition | D88: Target Definition | E88: Create New navigation And UI with a Gallery and a Add Target Button | F88: 1 | G88: 1 | I88: 1 | J88: 3 | K88: 3 | L88: 2.5
E89: Create Columns with name (Target definition listing displays Year, Period, Week, Punch Card Compliance Target (%), Weekly Observation Target per user, Week Start date, Week End Date and Action.) Action column will be the edit button inside gallery | J89: 2 | K89: 2
E90: Create a pop up on click of add target and create the same field inside the columns | J90: 2 | K90: 2
B92: Power Automate flows | C92: Email Notification | D92: Create a power automate flow for email notifications | J92: 7 | K92: 7 | L92: 1
C93: Export to excel | D93: create power automate flow to export the gallery details | J93: 10 | K93: 10 | L93: 1
B96: 3. Safety Officer (GMP) Aplication
B97: Sharepoint | C97: New Site | D97: Create Site | F97: 1 | G97: 1 | I97: 1 | J97: 2 | K97: 2
D98: Create Groups and Permissions | J98: 1 | K98: 1
D99: Create Table structure to map all the tables | J99: 6 | K99: 6
D100: Create Lists in Sharepoint | J100: 5 | K100: 5
D101: Create Views for the list | J101: 1 | K101: 1
A103: Dashboard screen | B103: Powerapps | C103: Dashboard | D103: Create a new UI screen and Navigation whch contains header columns as Main menu, Dashboard, Home, Observations, RCA, Reports,Admin site | F103: 1 | G103: 1 | I103: 1 | J103: 2 | K103: 2 | L103: 2
D104: Create a MU BBS Compliance per plant bar graph and MU Average BBS Compliance per calendar period line graph | E104: Power BI | F104: 1 | G104: 1 | I104: 1 | J104: 5 | K104: 5 | L104: 2
D105: Create a BBS MU Compliance per calendar period that displays a line graph which shows BBS compliance score of specific assigned plant as of current period. | F105: 1 | G105: 1 | I105: 1 | J105: 3 | K105: 3 | L105: 2
A107: Home screen | C107: Home Screen | D107: Create Home tab with new UI and navigation | E107: Crate a banner with notifictaion message for safety officer, conduct Observation Button and recent observations table list columns: Observer name, Observation Date, Plant, Task Observed and Area Observed. | F107: 1 | G107: 1 | I107: 1 | J107: 3 | K107: 3 | L107: 2
E108: Add No items to show.” message display when no recent observations were added or available. | J108: 2 | K108: 2
A110: Observations | C110: Observations | D110: Create New UI and Navigation with a Conduct Observation button | F110: 1 | G110: 1 | I110: 1 | J110: 3 | K110: 3 | L110: 4
D111: Create a shop checklist screen with new Navigation and UI | J111: 2 | K111: 2
D112: Shop checklist screen should contain Observer name , date observed plant, task observed, area observed | J112: 2 | K112: 2
D113: Create Yes/NO buttons for the following fields (Using appropriate tools, Always "Eyes on path", Safe position and location, Rightway of lifting, Following SOPs, Always 3 point contact, test, new test questions | J113: 2 | K113: 2
D114: Create a commendation field in text box given below the form | J114: 1 | K114: 1
D115: Create a Coaching provided field in text box | J115: 1 | K115: 1
D116: Create a Unsafe Condition Note field in text box | J116: 2 | K116: 2
D117: Create a submit buton to submit the checklist | J117: 1 | K117: 1
A119: RCA | C119: RCA | D119: Create new screen with UI Naviation | F119: 1 | G119: 1 | I119: 1 | J119: 2 | K119: 2 | L119: 3
D120: Gallery to display column date period, plant, performed by, location, status and action | J120: 3 | K120: 3
D121: Sort function beside each coloumn name | J121: 3 | K121: 3
...

Sheet Cadence
A1: Form Name | B1: EPIC | C1: User Story | D1: Task | E1: Sub Task | F1: PM | G1: BA | H1: Architect | I1: Tech Lead | J1: Dev in days | K1: Dev2 | L1: Test Lead | M1: QA Tester | N1: DBA | O1: DB Developer | P1: UX | Q1: UI
A2: Announcement | B2: Mobile Application | C2: Announcement | D2: Announcement Details | F2: 1 | G2: 1 | I2: 1 | J2: 1 | M2: 6
D3: Weekly Planner -Schedule sessions for the riders -Create a new session -Select drivers -Color coded for drivers for threshold criteria -Calendar view of all schedules | J3: 5
A4: DSP Route Ride | C4: DSP Route Ride | D4: Dashboard -Date filters -Search -Dashboard reports of all outlets that answers yes to the survey -Click graph to show survey result for the outlets | F4: 1 | G4: 1 | I4: 1 | J4: 3 | M4: 6
D5: Team Profile - DSP Rider information -Summary, Current Performance, Timeline | J5: 3
A6: DSP Route Ride | C6: Route Ride Session | D6: Start session -DSP Attendance form -Outlets selection (Choice) - Action items (Yes/No) Session Summary -4 input fields Further Remarks Remarks Input fields (Opportunities, Next Steps, Remarks etc.) Signature (can be desinatory digital signature or signature using pen input) End Session | F6: 1 | G6: 1 | I6: 1 | J6: 5 | M6: 5
D7: Summary -opportunities (Dynamic input fields) Current Performance -Training objectives etc. Timeline -Past activity -Audit logs like feature -Calendar view and click to view the activity | J7: 5
A8: Dashboard | C8: AAA+ Survey | D8: Dashboard | E8: 5 category reports (Available, Alam na meron, Ayos ang presyo, Dapat Malamig, Tottal AAA+ score) -Date filter -View Survey results | F8: 1 | G8: 1 | I8: 1 | J8: 5 | M8: 6
A9: Survey Form | D9: Survey Form | E9: Driver can only see this screen if they have a session scheduled -Display an info message Choose outlets and answer the form Form design is multiple input fields | J9: 5
A10: Survey Results | D10: Survey Results | E10: 2 Tab unsyn and sync AAA+ and Glass survey review Sync all survey/ Sync today | J10: 3
A11: Enroll Outlet | C11: Outlet Enrollment | D11: Enroll Outlet | E11: Fill form to enroll and outlet | F11: 1 | G11: 1 | I11: 1 | J11: 3 | M11: 5
A12: Outlets | D12: Outlets | E12: Outlet results (sync, unsyn tab to view each) Unsyc may be edited | J12: 3
A13: AD Dashboard | C13: AD Dashboard | D13: Power BI | E13: Need to understand if any modifications required or data can be directly connected | F13: 1 | G13: 1 | I13: 1 | J13: 5
A15: Survey Questions | B15: Web Application | C15: AAA+/Glass survey | D15: Survey Questions | E15: Survey Forms Searching questions Add New -Name -Questions (ability to add) -Question forms (This is dynamic needs to check) preview Delete Status (currently as colored icons) Edit | F15: 1 | G15: 1 | I15: 1 | J15: 5 | M15: 6
A16: Survey Reasons | D16: Survey Reasons | E16: Add survey reasons Search *Similar to survey forms in functionality | J16: 3
A17: Survey Schedule | D17: Survey Schedule | E17: Add schedule -New schedule form -Criterias and rules on some fields Upload Schedule -As per the export excel file format Filters/search/reset etc. -Download functonality Export to excel functionality (Could be power automate connected to SP) | J17: 3
A18: Report | D18: Report | E18: Data dashboard similar to survey forms Export/Download to excel functionality Filters Views | J18: 3
A19: Survey Questions | C19: Route Ride | D19: Survey Questions | E19: Similar to AAA survey questions All survey questions inputted here will be input in the AAA survey questions | F19: 1 | G19: 1 | I19: 1 | J19: 3 | M19: 6
A20: Route Ride Threshold criteria | D20: Route Ride Threshold criteria | E20: Configuration data Admin configurations for survey data criteria | J20: 5
A21: Objectives | D21: Objectives | E21: Objective data view Add new | J21: 2
A22: Route Ride Report | D22: Route Ride Report | E22: Data view of all route ride results Filters, search Export summary (From route ride dashboard) Export functionality | J22: 3
A23: Glass Survey | C23: Glass Survey | D23: Survey Questions | E23: Survey Forms Searching questions Add new preview Delete Status (currently as colored icons) Edit | F23: 1 | G23: 1 | I23: 1 | J23: 3 | M23: 6
A24: Report | D24: Report | E24: Data dashboard similar to survey forms Export/Download to excel functionality Filters Views | J24: 3
A25: Survey Frequency | C25: Survey Frequency | D25: Data view to view next visit for AAA and glass Filters Seach Reset | F25: 1 | G25: 1 | I25: 1 | J25: 3
A26: DSP Attendance | C26: DSP Attendance | D26: Similar to Survey reports/questions with data view All reports from mobile app Export funcitonality | F26: 1 | G26: 1 | I26: 1 | J26: 3 | M26: 4
A27: Enrolled outlets | C27: Enrolled outlets | D27: Similar to DSP reports/questions with data view All reports from mobile app Export funcitonality | F27: 1 | G27: 1 | I27: 1 | J27: 3 | M27: 4
A28: User Maintenance | C28: User Maintenance | D28: Announcements | E28: Data view Add announcements -Form to add new -Image upload Upload Edit Delete Export Filters/Search etc. Download template (This can be done backend) | F28: 1 | G28: 1 | I28: 1 | J28: 3 | M28: 6
D29: Survey Limit | E29: Data View Create New -Form to add new | I29: 1 | J29: 3
C31: Email Notifications | I31: 1 | J31: 2 | M31: 4
C33: DB Configuration | I33: 1 | J33: 5
A34: =COUNTA(A2:A33) -> 23 | B34: =COUNTA(B2:B33) -> 2 | C34: =COUNTA(C2:C33) -> 15 | D34: =COUNTA(D2:D33) -> 27 | E34: =COUNTA(E2:E33) -> 18 | F34: =SUM(F2:F33) -> 13 | G34: =SUM(G2:G33) -> 13 | H34: =SUM(H2:H33) -> 0 | I34: =SUM(I2:I33) -> 16 | J34: =SUM(J2:J33) -> 101 | K34: =SUM(K2:K33) -> 0 | L34: =SUM(L2:L33) -> 0 | M34: =SUM(M2:M33) -> 64 | ... Q34: =SUM(Q2:Q33) -> 0
D35: Days
B36: Total Development hours | C36: 808 | D36: 101
B37: Total Testing Hours | C37: 256 | D37: 32
B38: Requirement Gathering Hours | C38: 40 | D38: 5
B39: Data Migration | C39: 40 | D39: 5
B40: UAT | C40: 64 | D40: 8
B41: Go live
C43: 1208

Sheet Risk & Insurance
A1: From Name | B1: EPIC | C1: User Story | D1: Task | E1: Sub Task | F1: PM | G1: BA | H1: Architect | I1: Tech Lead | J1: DEV (Hours) | K1: QA Tester | L1: DBA | M1: DB Developer | N1: UX | O1: UI
B2: Mock Up Screens
B3: PowerApps | C3: Prepare Mockup Screens | D3: Create the Mockup Screens for all features | F3: 1 | G3: 1 | I3: 1 | J3: 30
B5: Sharepoint | C5: Sharepoint Site creation- Backend | D5: Create Site | F5: 1 | G5: 1 | I5: 1 | J5: 1
D6: Create Groups and Permissions | J6: 1
D7: Create Table structure to map all the tables | J7: 12
D8: Create Lists in Sharepoint | J8: 12
D9: Create Views for the list | J9: 6
A11: Login | B11: PowerApps | C11: Login Screen | D11: Create New Screen for to Login as Roles | E11: Banner, login button | F11: 1 | G11: 1 | I11: 1 | J11: 15 | K11: 4
D12: Bug fixig | J12: 3
A14: Admin Home | C14: Admin Home Screen | D14: Create New screen with UI Navigations | F14: 1 | G14: 1 | I14: 1 | J14: 5 | K14: 5
D15: Create Gallery to show the Master List of Vechiles details | J15: 15
D16: Create Search and Sorting Function based of Insurance type | J16: 6
D17: Bug fixig | J17: 5
C19: Maintenance Modules | D19: Create New Screen to Add/Update Below Modules | F19: 1 | G19: 1 | I19: 1 | J19: 8
A20: Users | D20: Users | E20: users (Requestor,Broker,Claim Approver, Loa Approver) can be created, this consists of search by filter, reset and action which includes edit and delete. | J20: 24 | K20: 6
E21: Testing and Bug fixig | J21: 5
A22: Claims | D22: Claims Documents | E22: Search, filter, to create new documnet type. | J22: 18 | K22: 6
E23: Testing and Bug fixig | J23: 4
A24: Service Centers | D24: Service centers | E24: search, reset and to create new service center which also includes the action of edit and delete | J24: 18 | K24: 6
E25: Testing and Bug fixig | J25: 4
A26: Adjusters | D26: Adjusters | E26: Actions including edit, delete and create new adjusters. Search and filter | J26: 18 | K26: 6
E27: Testing and Bug fixig | J27: 4
A28: Regions | D28: Regions | E28: Add new ,delete,Edit Regions. Search and filter fuction | J28: 18 | K28: 6
E29: Testing and Bug fixig | J29: 4
A30: Plants | D30: Plants | E30: Add new ,delete, Edit Plants. Search and filter fuction | J30: 18 | K30: 6
E31: Testing and Bug fixig | J31: 4
A32: Vechile Types | D32: Vehicle types | E32: Add new, delete, Edit Vechile type. Search and filter fuction | J32: 18 | K32: 6
E33: Testing and Bug fixig | J33: 4
A34: Asset Class | D34: Asset class | E34: Add new, delete, Edit Asset class. Search and filter fuction | J34: 18 | K34: 6
E35: Testing and Bug fixig | J35: 4
C37: Requestor Screen | D37: Gallery list to show cliams submitted | F37: 1 | G37: 1 | I37: 1 | J37: 14 | K37: 8
D38: Create Search for claims based on data range | J38: 4
D39: Button to create a claim | J39: 3
D40: Create form - Includes Motor vehicle, Claim type and Documents | J40: 6 | K40: 3
D41: Submit function to save the details | J41: 3
D42: Bug fixig | J42: 8
A44: Claims Documents | C44: View Screen | D44: View the claim form | F44: 1 | G44: 1 | I44: 1 | J44: 14 | K44: 6
D45: Can edit/upload document | J45: 4
D46: Submit function to save the details | J46: 6
D47: Bug fixig | J47: 5
C49: Approver | D49: View the claim form | F49: 1 | G49: 1 | I49: 1 | J49: 6 | K49: 5
D50: Approve /Reject button with popup | J50: 4
D51: Bug fixig | J51: 5
A53: Dashboard | B53: PowerBI | C53: Dashborad Screen | D53: To display chart of settled claim and outstanding claim | F53: 1 | G53: 1 | I53: 1 | J53: 16 | K53: 6
D54: Bug fixig | J54: 2
B56: Power Automate Flow | C56: Email Notification flows | D56: Email Notifiation on submission of claim request | F56: 1 | G56: 1 | I56: 1 | J56: 5 | K56: 3
D57: Email notification on Appove rejects actions | J57: 5 | K57: 2
D58: Email flow to extract file from sftp folder | E58: Motor vehicles (vehicles are managed), where they get data synced with SAP via SFTP and can edit the details. Two files are extracted which includes Asset and Equipment where Asset consists of identification number (asset number) and Equipment consists of vehicle information. | J58: 20 | K58: 6
A59: =COUNTA(A1:A58) -> 13 | B59: =COUNTA(B27:B58) -> 2 | C59: =COUNTA(C27:C58) -> 5 | D59: =COUNTA(D27:D58) -> 22 | E59: =COUNTA(E27:E58) -> 10
B60: Total Hours | F60: =SUM(F1:F58) -> 10 | G60: =SUM(G1:G58) -> 10 | I60: =SUM(I1:I58) -> 10 | J60: =SUM(J1:J58) -> 432 | K60: =SUM(K1:K58) -> 96 | L60: =SUM(L1:L58) -> 0 | M60: =SUM(M1:M58) -> 0 | N60: =SUM(N1:N58) -> 0 | O60: =SUM(O1:O58) -> 0
D62: Hours | E62: Days | I62: Total dev Days | J62: =(J60/8) -> 54 | K62: =(K60/8) -> 12
C63: Total Development hours | D63: =J60 -> 432 | E63: =J62 -> 54
C64: Total Testing Hours | D64: =K60 -> 96 | E64: =K62 -> 12
C65: Requirement Gathering Hours | D65: 64 | E65: 8 | J65: =60*8 -> 480 | K65: =15*8 -> 120
C66: Data Migration | D66: 24 | E66: 3
C67: UAT | D67: 64 | E67: 8
C68: Go live
C70: Total hours/DAYS | D70: =SUM(D63:D68) -> 680 | E70: =SUM(E63:E68) -> 85

Sheet CAF Effort
A1: EPIC | B1: User Story | C1: Task | D1: Sub Task | E1: PM | F1: BA | G1: Architect | H1: Tech Lead | I1: Dev1 | J1: Dev2 | K1: Test Lead | L1: Test Engineer | M1: DBA | N1: DB Developer | O1: UX | P1: UI
B2: Customer Login | E2: 5 | F2: 5 | G2: 5 | H2: 8 | I2: 10 | J2: 10 | K2: 3 | L2: 6 | M2: 1 | N2: 1 | O2: 2 | P2: 2
C3: Get Link
C4: Update Details
C5: Verify and Login
C6: Authorization
C7: Forgot Password
C8: Back to email
C9: SSO Integration
B10: Admin Dashbaord | E10: 1 | F10: 1 | G10: 1 | H10: 2 | I10: 2 | J10: 2 | K10: 1 | L10: 2 | M10: 2 | N10: 3 | O10: 2 | P10: 3
C11: Menu
C12: List View
B13: Admin Portal
C14: Config Setup | E14: 1 | F14: 1 | G14: 1 | H14: 2 | I14: 2 | J14: 2 | K14: 1 | L14: 2 | M14: 2 | N14: 3 | O14: 2 | P14: 4
C15: Admin User Setup | E15: 2 | F15: 2 | G15: 2 | H15: 3 | I15: 5 | J15: 5 | K15: 1 | L15: 3 | M15: 1 | N15: 3 | O15: 2 | P15: 3
D16: Search
D17: List View
D18: Reset
D19: Add Existing User
D20: List view
D21: Add all
D22: Cancel
D23: List View
D24: Remove
C25: Role Details Setup | E25: 2 | F25: 2 | G25: 2 | H25: 3 | I25: 5 | J25: 5 | K25: 1 | L25: 3 | M25: 1 | N25: 3 | O25: 2 | P25: 3
D26: Auto Create Role Setup
D27: Save
D28: Remove
D29: List View
C30: Route Code Email Setup
C31: General Trade | E31: 2 | F31: 2 | G31: 2 | H31: 3 | I31: 5 | J31: 5 | K31: 1 | L31: 3 | M31: 1 | N31: 3 | O31: 2 | P31: 3
D32: List View
D33: Select File & Import Data
D34: Download Data
D35: Setup Data
D36: Save
C38: Modern Trade | E38: 1 | F38: 1 | G38: 1 | H38: 2 | I38: 2 | J38: 2 | K38: 1 | L38: 2 | M38: 2 | N38: 3 | O38: 2 | P38: 3
D39: List View
B40: Audit Logs | E40: 3 | F40: 3 | G40: 3 | H40: 4 | I40: 8 | J40: 8 | K40: 3 | L40: 5 | M40: 3 | N40: 5 | O40: 3 | P40: 5
C41: List View
C42: Audit Logs
D43: Expand Details
C44: Quick Logs
D45: View
C46: Trigger Audit Log Time | D46: Schedular
B47: Internal Users/Intenal Roles
C48: Download All Users | E48: 1 | F48: 1 | G48: 1 | H48: 2 | I48: 2 | J48: 2 | K48: 1 | L48: 2 | M48: 1 | N48: 2 | O48: 1 | P48: 2
D49: List View
D50: View Users
C52: Modern Trade | E52: 1 | F52: 1 | G52: 1 | H52: 2 | I52: 2 | J52: 2 | K52: 1 | L52: 2 | M52: 1 | N52: 2 | O52: 1 | P52: 1
D53: List View
D54: View Users
D55: Add
D56: Back
D57: List View
D58: Remove
C59: General Trade | E59: 1 | F59: 1 | G59: 1 | H59: 2 | I59: 2 | J59: 2 | K59: 1 | L59: 2 | M59: 1 | N59: 2 | O59: 1 | P59: 1
D60: List View
D61: View Users
D62: Add
D63: Back
D64: List View
D65: Remove
C66: Special | E66: 1 | F66: 1 | G66: 1 | H66: 2 | I66: 2 | J66: 2 | K66: 1 | L66: 2 | M66: 2 | N66: 2 | O66: 1 | P66: 1
D67: List View
D68: View Users
D69: Add
D70: Back
D71: List View
D72: Remove
B73: Approvers | E73: 3 | F73: 3 | G73: 3 | H73: 4 | I73: 8 | J73: 8 | K73: 3 | L73: 5 | M73: 3 | N73: 5 | O73: 3 | P73: 5
C74: List View
C75: Search
C76: Reset
C77: Select File
C78: Upload File
C79: Download Template
C80: Download Records
C81: Clear Records
C82: Modern Trade
D83: Trade
D84: Finance
C85: General Trade
D86: Trade
D87: Finance
B89: Approval Metrix | E89: 1 | F89: 1 | G89: 1 | H89: 2 | I89: 2 | J89: 2 | K89: 1 | L89: 2 | M89: 1 | N89: 1 | O89: 1 | P89: 2
C90: List View
C91: Credit Application | E91: 5 | F91: 5 | G91: 5 | H91: 7 | I91: 12 | J91: 12 | K91: 3 | L91: 5 | M91: 5 | N91: 8 | O91: 6 | P91: 9
C92: Modern Trade
D93: List View
D94: Back
D95: Add/Edit
D96: Load Details
D97: Actions
D98: Remove
C99: General Trade
D100: List View
D101: Back
D102: Add/Edit
D103: Load Details
...

Sheet CWT Effort
A1: EPIC | B1: User Story | C1: Task | D1: Sub Task | E1: Web Forms | F1: PM | G1: BA | H1: Architect | I1: Tech Lead | J1: Dev1 | K1: Dev2 | L1: Test Lead | M1: Test Engineer | N1: DBA | O1: DB Developer | P1: UX | Q1: UI
B2: Logo & Menu | E2: Authentication & Authorization | F2: 1 | G2: 1 | H2: 1 | I2: 2 | J2: 3 | K2: 3 | L2: 1 | M2: 2 | N2: 1 | O2: 2 | P2: 2 | Q2: 3
C3: Login Lable | E3: Reports
C4: Logo | E4: Extract
C5: Logout | E5: List View
C6: App Menu items | E6: Certificates
B7: Login Feature | E7: Preview | F7: 2 | G7: 2 | H7: 3 | I7: 4 | J7: 6 | K7: 6 | L7: 2 | M7: 3 | N7: 1 | O7: 2 | P7: 2 | Q7: 3
C8: Login | E8: List View
C9: Remember Me | E9: Vendors
C10: Forgot Password | E10: Bulk Upload
C11: Authorization | E11: Add
C12: Logout | E12: Import
B13: Certificates | E13: Edit | F13: 3 | G13: 3 | H13: 3 | I13: 6 | J13: 8 | K13: 8 | L13: 3 | M13: 5 | N13: 1 | O13: 2 | P13: 2 | Q13: 3
C14: Search | E14: Maintenence
C15: Preview | E15: Users List
C16: List View | E16: Create User
C17: Download | E17: Edit User
C18: Back | E18: Audit Lots
B19: Vendors | E19: CWT Changes | F19: 3 | G19: 3 | H19: 4 | I19: 6 | J19: 9 | K19: 9 | L19: 3 | M19: 6 | N19: 2 | O19: 5 | P19: 3 | Q19: 5
C20: Search | E20: Configuration
C21: List View | E21: Tax Codes
C22: Create Vendor | E22: Bulk Upload
C23: Exxtract Vendors | E23: Create Tax Codes
C24: Edit Vendor
C25: Bulk Upload
C26: Cancel
A27: Maintainance
B28: Users | F28: 2 | G28: 2 | H28: 3 | I28: 4 | J28: 6 | K28: 6 | L28: 4 | M28: 6 | N28: 3 | O28: 5 | P28: 3 | Q28: 4
C29: Search
C30: List View
C31: Create User
C32: Edit User
C33: Delete User
C34: Cancel
B35: Audit Logs | F35: 2 | G35: 2 | H35: 2 | I35: 2 | J35: 4 | K35: 4 | L35: 2 | M35: 4 | N35: 2 | O35: 4 | P35: 2 | Q35: 3
C36: Search
C37: List View
B38: CWT Changes | F38: 2 | G38: 2 | H38: 2 | I38: 2 | J38: 4 | K38: 4 | L38: 2 | M38: 4 | N38: 2 | O38: 4 | P38: 2 | Q38: 3
C39: Search
C40: List View
B41: Company Codes | F41: 3 | G41: 3 | H41: 3 | I41: 4 | J41: 6 | K41: 6 | L41: 3 | M41: 5 | N41: 2 | O41: 4 | P41: 3 | Q41: 4
C42: Search
C43: List View
C44: Create Company
C45: Edit Company
C46: Cancel
B47: Configuration | F47: 4 | G47: 4 | H47: 4 | I47: 6 | J47: 10 | K47: 10 | L47: 6 | M47: 8 | N47: 4 | O47: 7 | P47: 5 | Q47: 7
C48: SFTP Settings
C49: Custom Calendar
C50: CWT Custom Template
B51: Tax Codes | F51: 2 | G51: 2 | H51: 3 | I51: 4 | J51: 6 | K51: 6 | L51: 4 | M51: 6 | N51: 3 | O51: 5 | P51: 3 | Q51: 4
C52: Search
C53: List View
C54: Create Tax Code
C55: Edit Tax Code
C56: Upload From File
C57: Cancel
B58: Reports | F58: 3 | G58: 3 | H58: 3 | I58: 4 | J58: 6 | K58: 6 | L58: 3 | M58: 5 | N58: 2 | O58: 4 | P58: 3 | Q58: 4
C59: Search
C60: List View
C61: Reset
C62: Extract to Excel
B63: Email Functionality | F63: 2 | G63: 2 | H63: 2 | I63: 3 | J63: 5 | K63: 5 | L63: 2 | M63: 3 | N63: 1 | O63: 2 | P63: 2 | Q63: 3
B64: Windows Schedular | F64: 3 | G64: 3 | H64: 4 | I64: 4 | J64: 8 | K64: 8 | L64: 4 | M64: 8 | N64: 2 | O64: 5 | P64: 4 | Q64: 5
B66: =COUNTA(Table9[User Story]) -> 13 | C66: =COUNTA(Table9[Task]) -> 49 | D66: =COUNTA(Table9[Sub Task]) -> 0 | E66: =COUNTA(Table9[Web Forms]) -> 22

Sheet Digitalized Invoice Effort
A1: Epic | B1: User Story | C1: Task | D1: Sub Task | E1: Web Forms | F1: PM | G1: BA | H1: Architect | I1: Tech Lead | J1: Dev1 | K1: Dev2 | L1: Test Lead | M1: Test Engineer | N1: DBA | O1: DB Developer | P1: UX | Q1: UI | R1: Cloud Architect | S1: DevOps Engineer
A2: Login Feature | E2: Dashboard | R2: 20 | S2: 20
B3: Login | E3: Reports | F3: 1 | G3: 1 | H3: 2 | I3: 2 | J3: 3 | K3: 3 | L3: 1 | M3: 2 | N3: 1 | O3: 1 | P3: 2 | Q3: 2
B4: SSO | E4: Audit Logs
B5: Authorization | E5: Print Logs
B6: Password Change | E6: Approver Logs
B7: Logout | E7: Email Logs
A8: Dashboard | E8: Invoice Logs | F8: 1 | G8: 1 | H8: 1 | I8: 2 | J8: 3 | K8: 3 | L8: 2 | M8: 1 | N8: 1 | O8: 2 | P8: 3 | Q8: 3
B9: Total Count of Invoices | E9: Maintenance
B10: Total amount due | E10: Approver List
B11: total count of re-print | E11: Add
B12: Total count of pending | E12: Edit
B13: Search - Location filter | E13: Bulk Add
B14: Search - Dare filter | E14: Select
A15: Report | E15: Customer | F15: 2 | G15: 2 | H15: 2 | I15: 3 | J15: 5 | K15: 5 | L15: 2 | M15: 3 | N15: 1 | O15: 2 | P15: 2 | Q15: 3
B16: Filter Report | E16: Add
B17: Export Report | E17: Edit
B18: Report List View | E18: Bulk Add
E19: Select
A20: Audit Logs | E20: Customer Group | F20: 4 | G20: 4 | H20: =SUM(H21:H30) -> 0 | I20: 8 | J20: 12 | K20: 12 | L20: 8 | M20: 12 | N20: 4 | O20: 8 | P20: 8 | Q20: 8
B21: Print Log | C21: Filter Search | E21: Add
C22: Export Report | E22: Edit
C23: List View | E23: Bulk Add
B24: Approver Log | C24: Filter Search | E24: Select
C25: Export Report | E25: Configuration
C26: List View | E26: Commercial Unit
B27: Email Log | C27: Filter Search | E27: Add
C28: Export Report | E28: Edit
C29: List View | E29: Bulk Add
B30: Invoice Log | C30: Filter Search | E30: Select
C31: Export Report | E31: Invoice Footer
C32: List View | E32: Add
A33: Maintainance | E33: Edit | F33: 2 | G33: 2 | H33: 2 | I33: 3 | J33: 5 | K33: 5 | L33: 2 | M33: 3 | N33: 2 | O33: 3 | P33: 3 | Q33: 4
B34: Approver List | E34: Bulk Add
C35: Search Filter | E35: Select
C36: Approvers without location | E36: Location
C37: List View | E37: Add
C38: Bulk Upload | E38: Edit
D39: Download Template | E39: Bulk Add
D40: Upload file | E40: Select
C41: Add Approver | E41: Sales Group | F41: 2 | G41: 2 | H41: 2 | I41: 3 | J41: 5 | K41: 5 | L41: 2 | M41: 3 | N41: 2 | O41: 3 | P41: 3 | Q41: 4
D42: Personal Information | E42: Add
D43: Additional Information | E43: Edit
D44: User Status | E44: Bulk Add
D45: Approver Type | E45: Select
D46: Add Locarion | E46: Sales Office
D47: List Location | E47: Add
C48: Edit Approver | E48: Edit | F48: 1 | G48: 1 | H48: 1 | I48: 1 | J48: 2 | K48: 2 | L48: 1 | M48: 2 | N48: 1 | O48: 2 | P48: 1 | Q48: 1
E49: Bulk Add
B50: Customer | E50: Select | F50: 2 | G50: 2 | H50: 2 | I50: 3 | J50: 5 | K50: 5 | L50: 2 | M50: 3 | N50: 2 | O50: 3 | P50: 3 | Q50: 4
C51: Bulk Upload | E51: Sales Org
C52: Add Customer | E52: Add
C53: List View | E53: Edit
C54: Activate | E54: Bulk Add
C55: De-Activate | E55: Select
B56: Customer Group | E56: Site Admin | F56: 1 | G56: 1 | H56: 1 | I56: 2 | J56: 3 | K56: 3 | L56: 2 | M56: 3 | N56: 1 | O56: 2 | P56: 2 | Q56: 2
C57: Bulk upload | E57: Add
C58: Add Customer Group | E58: Edit
C59: Edit Customer | E59: Bulk Add
B60: Configuration | E60: Select | F60: 1 | G60: 1 | H60: 1 | I60: 2 | J60: 3 | K60: 3 | L60: 2 | M60: 3 | N60: 1 | O60: 2 | P60: 2 | Q60: 2
C61: Customer Group Entries UI | E61: Authentication & Authorization
C62: Send Email | E62: Send Notification
C63: Send SMS | E63: Win Schedular
B64: Commercial Unit | E64: Download Template | F64: 1 | G64: 1 | H64: 1 | I64: 2 | J64: 3 | K64: 3 | L64: 2 | M64: 3 | N64: 1 | O64: 2 | P64: 2 | Q64: 2
C65: Bulk upload | E65: Upload file
C66: Add Unit | E66: Personal Information
E67: Additional Information
E68: User Status
B69: Invoice Footer | E69: Approver Type | F69: 1 | G69: 1 | H69: 1 | I69: 2 | J69: 3 | K69: 3 | L69: 2 | M69: 3 | N69: 1 | O69: 2 | P69: 2 | Q69: 2
C70: Add Invoice Footer | E70: Add
C71: Edit Invoice Footer | E71: Edit
C72: Filter Search | E72: Bulk Add
C73: List View | E73: Select
E74: Add Locarion
B75: Location | E75: Add | F75: 2 | G75: 2 | H75: 2 | I75: 3 | J75: 5 | K75: 5 | L75: 2 | M75: 3 | N75: 2 | O75: 3 | P75: 3 | Q75: 4
C76: Bulk Upload | E76: Edit
C77: Add Location | E77: Bulk Add
C78: Save Location | E78: Select
C79: Cancel Location | E79: List Location
C80: List View | E80: Add
B81: Sales Group | E81: Edit | F81: 2 | G81: 2 | H81: 2 | I81: 3 | J81: 5 | K81: 5 | L81: 2 | M81: 3 | N81: 2 | O81: 3 | P81: 3 | Q81: 4
C82: Bulk Upload | E82: Bulk Add
C83: Add Sales Group | E83: Select
C84: Edit Sales Group
C85: Cancel Sales Group
C86: List View
B87: Sales Office | F87: 2 | G87: 2 | H87: 2 | I87: 3 | J87: 5 | K87: 5 | L87: 2 | M87: 3 | N87: 2 | O87: 3 | P87: 3 | Q87: 4
C88: Bulk Upload
C89: Add Sales Office
C90: Edit Sales Office
C91: Cancel Sales Office
C92: List View
B93: Sales Org | F93: 2 | G93: 2 | H93: 2 | I93: 3 | J93: 5 | K93: 5 | L93: 2 | M93: 3 | N93: 2 | O93: 3 | P93: 3 | Q93: 4
C94: Bulk Upload
C95: Add Sales Org
C96: Edit Sales Org
C97: Cancel Sales Org
C98: List View
B99: Site Admin | F99: 2 | G99: 2 | H99: 2 | I99: 3 | J99: 5 | K99: 5 | L99: 2 | M99: 3 | N99: 2 | O99: 3 | P99: 3 | Q99: 4
C100: Add Site Admin
...

Sheet Survey App Details
A1: EPIC | B1: User Story | C1: Task | D1: Sub Task | E1: PM | F1: BA | G1: Architect | H1: Tech Lead | I1: Dev1 | J1: Dev2 | K1: Test Lead | L1: Test Engineer | M1: DBA | N1: DB Developer | O1: UX | P1: UI | Q1: Cloud Architect | R1: DevOps Engineer
B2: Login features
C3: Login
C4: Forgot password
C5: Remember Me
C6: Logout
C7: Authorization
B8: Side Pane
C9: Account settings | D9: User details
D10: Change password
C11: Menu
A12: Users
B13: Manage users
C14: Search
C15: Reset
C16: Export
C17: List view
C18: Add user
C19: Add multiple user | D19: Download user template
D20: Download user assignment template
D21: upload file
D22: Edit user
D23: Cancel & Back
A24: User assignment
B25: Department
C26: Search
C27: Export
C28: List view
C29: Add Department
C30: Edit Department
B31: Customer group
C32: Search
C33: Export
C34: List view
C35: Add customer group
C36: Add multiple customer group | D36: Download template
D37: Upload file
D38: Cancel & Back
C39: Edit customer group
B40: Territory
C41: Search
C42: Export
C43: List view
C44: Add Territory
C45: Edit Territory
B46: Commericial unit
C47: Search
C48: Export
C49: List view
C50: Add commercial unit
C51: Add multiple commercial unit | D51: Download template
D52: Upload file
D53: Cancel & Back
C54: Edit commercial unit
B55: Region
C56: Search
C57: Export
C58: List view
C59: Add region
C60: Add multiple region | D60: Download region template
D61: Download commericial unit template
D62: Download territory data template
D63: Upload file
D64: Cancel & Back
C65: Edit commercial unit
B66: Sales location
C67: Search
C68: Export
C69: List view
C70: Add sales location
C71: Add multiple sales location | D71: Download sales location template
D72: Download region template
D73: Upload file
D74: Cancel & Back
C75: Edit sales location
A76: Surveys
B77: Survey List View
B78: Dashboard
C79: Total Survey
C80: Published
C81: Draft
C82: Expired
C83: Closed
C84: Actions
D85: Duplicate Report
D86: Download Export Report
D87: Close Survey
D88: View Respondents
B89: Surveys | D89: Preview Survey
C90: Search
C91: Create Survey | D91: Question display
C92: Add section
C93: Add Question | D93: Select type of question
D94: Edit question
D95: Delete question
D96: Change question type
D97: Move to section
C98: Edit Survey | D98: Question display
C99: Add section
C100: Add Question | D100: Select type of question
...

Sheet Survey App Effort
A1: EPIC | B1: User Story | C1: Task | D1: Sub Task | E1: Web Forms | F1: PM | G1: BA | H1: Architect | I1: Tech Lead | J1: Dev1 | K1: Dev2 | L1: Test Lead | M1: Test Engineer | N1: DBA | O1: DB Developer | P1: UX | Q1: UI | R1: Cloud Architect | S1: DevOps Engineer
B2: Login features | E2: Authentication & Authorization | F2: 1 | G2: 1 | H2: 2 | I2: 2 | J2: 3 | K2: 3 | L2: 1 | M2: 2 | N2: 1 | O2: 1 | P2: 2 | Q2: 2
C3: Login | E3: Send Notification
C4: Forgot password | E4: Windows Schedular
C5: Remember Me | E5: Users
C6: Logout | E6: Add
C7: Authorization | E7: Manage
B8: Side Pane | E8: Bulk Add | F8: 1 | G8: 1 | H8: 1 | I8: 1 | J8: 2 | K8: 2 | L8: 1 | M8: 1 | N8: 1 | O8: 1 | P8: 1 | Q8: 2
C9: Account settings | E9: User Assignment
D10: User details | E10: Department
D11: Change password | E11: Add
C12: Menu | E12: Customer Group
A13: Users | E13: Add
B14: Manage users | E14: Bulk Add | F14: 2 | G14: 2 | H14: 2 | I14: 3 | J14: 5 | K14: 5 | L14: 2 | M14: 3 | N14: 1 | O14: 2 | P14: 3 | Q14: 3
C15: Search
C16: Reset
C17: Export
C18: List view
C19: Add user
C20: Add multiple user | F20: 3 | G20: 3 | H20: 3 | I20: 4 | J20: 5 | K20: 5 | L20: 2 | M20: 4 | N20: 1 | O20: 2 | P20: 4 | Q20: 4
D21: Download user template
D22: Download user assignment template
D23: Upload file
D24: Edit user
D25: Cancel & Back
A26: User assignment
B27: Department
C28: Search | F28: 2 | G28: 2 | H28: 1 | I28: 2 | J28: 3 | K28: 3 | L28: 2 | M28: 3 | N28: 1 | O28: 2 | P28: 2 | Q28: 2
C29: Export
C30: List view
C31: Add Department
C32: Edit Department
B33: Customer group | F33: 2 | G33: 2 | H33: 2 | I33: 3 | J33: 5 | K33: 5 | L33: 2 | M33: 3 | N33: 1 | O33: 2 | P33: 2 | Q33: 3
C34: Search
C35: Export
C36: List view
C37: Add customer group
C38: Add multiple customer group
D39: Download template
D40: Upload file
D41: Cancel & Back | E41: Territory
C42: Edit customer group | E42: Add
B43: Territory | F43: 2 | G43: 2 | H43: 1 | I43: 2 | J43: 3 | K43: 3 | L43: 2 | M43: 3 | N43: 1 | O43: 2 | P43: 2 | Q43: 2
C44: Search
C45: Export
C46: List view
C47: Add Territory | E47: Commericial unit
C48: Edit Territory | E48: Add
B49: Commericial unit | E49: Bulk Add | F49: 2 | G49: 2 | H49: 2 | I49: 3 | J49: 5 | K49: 5 | L49: 2 | M49: 3 | N49: 1 | O49: 2 | P49: 2 | Q49: 3
C50: Search
C51: Export
C52: List view
C53: Add commercial unit
C54: Add multiple commercial unit
D55: Download template
D56: Upload file | E56: Region
D57: Cancel & Back | E57: Add
C58: Edit commercial unit | E58: Bulk Add
B59: Region | F59: 2 | G59: 2 | H59: 2 | I59: 3 | J59: 5 | K59: 5 | L59: 2 | M59: 3 | N59: 1 | O59: 2 | P59: 2 | Q59: 3
C60: Search
C61: Export
C62: List view
C63: Add region
C64: Add multiple region
D65: Download region template
D66: Download commericial unit template
D67: Download territory data template | E67: Sales location
D68: Upload file | E68: Add
D69: Cancel & Back | E69: Bulk Add
C70: Edit commercial unit
B71: Sales location
C72: Search | F72: 2 | G72: 2 | H72: 2 | I72: 3 | J72: 5 | K72: 5 | L72: 2 | M72: 3 | N72: 1 | O72: 2 | P72: 2 | Q72: 3
C73: Export
C74: List view
C75: Add sales location
C76: Add multiple sales location
D77: Download sales location template
D78: Download region template | E78: Survey List View
D79: Upload file | E79: Add
D80: Cancel & Back | E80: Bulk Add
C81: Edit sales location | E81: Dash Board
A82: Surveys
B83: Survey List View | F83: 2 | G83: 2 | H83: 2 | I83: 3 | J83: 5 | K83: 5 | L83: 2 | M83: 3 | N83: 1 | O83: 2 | P83: 2 | Q83: 3
C84: Dashboard
C85: Total Survey
C86: Published
C87: Draft
C88: Expired
C89: Closed
C90: Actions
D91: Duplicate Report
D92: Download Export Report | E92: Dash Board
D93: Close Survey | E93: Add
D94: View Respondents | E94: Bulk Add
D95: Preview Survey | E95: Delete
A96: Surveys | E96: Display | F96: 7 | G96: 7 | H96: 7 | I96: 10 | J96: 15 | K96: 15 | L96: 8 | M96: 15 | N96: 8 | O96: 15 | P96: 10 | Q96: 12
B97: Dash Board & List View | E97: Move Section
C98: Search | E98: Change Question
C99: Create Survey | E99: Add Section
C100: Add section
...

Sheet Survey Mobile App
A1: EPIC | B1: User Story | C1: Task | D1: Sub Task | E1: PM | F1: BA | G1: Architect | H1: Tech Lead | I1: Dev1 | J1: Dev2 | K1: Test Lead | L1: Test Engineer | M1: DBA | N1: DB Developer | O1: UX | P1: UI | Q1: Cloud Architect | R1: DevOps Engineer
B2: Authentication | E2: 2 | F2: 2 | G2: 2 | H2: 3 | I2: 5 | J2: 5 | K2: 2 | L2: 3 | M2: 1 | N2: 2 | O2: 2 | P2: 3
C3: Login
C4: Forgot Password
C5: Logout
B6: Surveyor List | E6: 4 | F6: 4 | G6: 4 | H6: 6 | I6: 8 | J6: 8 | K6: 3 | L6: 4 | M6: 2 | N6: 4 | O6: 5 | P6: 7
C7: Survey list
C8: Syncronized
D9: View survey response
C10: Not Syncronized
C11: Submit all response
C12: Sync survey list
C13: Sync survey respondents
C14: Add respone
D15: Terms policy
D16: Save survey response
E17: =SUM(Table57[PM]) -> 6 | F17: =SUM(Table57[BA]) -> 6 | G17: =SUM(Table57[Architect]) -> 6 | H17: =SUM(Table57[Tech Lead]) -> 9 | I17: =SUM(Table57[Dev1]) -> 13 | J17: =SUM(Table57[Dev2]) -> 13 | K17: =SUM(Table57[Test Lead]) -> 5 | L17: =SUM(Table57[Test Engineer]) -> 7 | M17: =SUM(Table57[DBA]) -> 3 | N17: =SUM(Table57[DB Developer]) -> 6 | O17: =SUM(Table57[UX]) -> 7 | P17: =SUM(Table57[UI]) -> 10

Sheet JDs
A1: SDM
A2: Project Manager | B2: Total Experience:10-12 Years Agile, Scrum, ITIL & PMP certiffied Technical ManagerReview existing solutions, identify opportunities for continuous improvements, and perform enhancements to systems. Understand .NET & Cloud systems architecture with high customization and complex business process and recommend/implement scalable solutions. Manage systems integrations to/from the application and assist in data transfers. Work with infrastructure team to ensure the public cloud environment is tuned to optimum efficiency. Manage SLAs and guide the team to triage, identify and recommend technical solutions for fixing issues and enhancements. Collaborate and work with business and cross-functional teams to identify & implement effective solutions that automates and optimizes system performance and business processes, including scaling cloud-native applications.
A3: UX | B3: Total Experience:5-6 Years Strong proficiency in HTML, CSS, JavaScript, and ASP.NET Razor syntax, Experience with front-end frameworks/libraries (e.g., jQuery, Bootstrap), Familiarity with responsive web design and mobile-first development, Knowledge of ASP.NET MVC and ASP.NET Web API, Understanding of browser developer tools for debugging, Experience with Visual Studio or other ASP.NET development tools, Excellent problem-solving and communication skills, Attention to detail and a strong eye for design, Ability to work both independently and collaboratively in a team environment, Portfolio of previous web development projects, especially those involving ASP.NET
A4: UI | B4: Total Experience:5-6 Years Collaborate with back-end developers to seamlessly integrate user interfaces with ASP.NET applications, Create visually appealing and responsive web pages using HTML, CSS, JavaScript, and ASP.NET Razor syntax, UI/UX Implementation: Transform design concepts into interactive web elements, maintaining design consistency and optimizing user experience, Develop components to display and manipulate data retrieved from ASP.NET APIs or databases, Client-Side Scripting: Write scripts to enhance user interactivity and validate user input, Cross-Browser Compatibility: Ensure web applications function correctly across various browsers and devices, Performance Optimization: Optimize web pages for speed and efficiency to minimize load times, Responsive Design: Implement layouts that adapt to different screen s and resolutions. Code Quality: Write clean, well-documented, and maintainable code following ASP.NET and industry best practices
A5: BA | B5: Total Experience:6-8 Years Proficient in Food and Bevarages industry, retail, wholesale, taxation, Finance and credit applications Analyzing data, creating FSD, BRD, identifying business processes, and translating business requirements into technical specifications. He/She should communicate with stakeholders to ensure that the business needs are met.
A6: Pre-Sales Solution Architect | B6: Total Experience:14-18 Years Pre-Sales Soluiton Achitect having relevant Microsoft Azure architecture, design & delivery experience Consulting experience with large-scale implementations on Microsoft Azure Experience in Azure Infra, Networks, Storage, Apps and Azure DevOps Experience in Creating solutions, presenting and articulating winning prepositions for Microsoft Azure Well versed with cloud architecture styles and design patterns Experience in developing cloud migration approaches, defining migration roadmaps and providing estimates Experience with Azure Resource Manager, Resource Groups, Virtual Networks, Azure Virtual Machines, Azure Blob Storage, PowerShell DSC, Azure Automation, Azure Active Directory, and Azure Site Recovery Experience in developing and deploying Cloud Native Applications using Azure PaaS Capabilities (App Services Plans, Key Vault, SQL Azure DB, Azure Functions, Containers, AKS, Logic Apps, Service Bus, Event Grid, API Management) Experience in Enterprise Integration Technologies such as BizTalk, Azure API Management, Logic Apps, Service Bus Demonstrates strong analytical and technical problem-solving skills
A7: Azure Cloud Architecture | B7: Total Experience:10-12 Years Primary Skills: az305, az104 Azure Solution Architect. Azure- Infra, Security, Mornitoring, Data & Storage, Networking, Compute, Analytics, DevSecOps, Web & Mobile, Fabric, ASP.Net Core, PaaS, IaaS, FaaS, SaaS Secondary: Knowlodege on application migration and modernization, Best Practices, Azure Cost Factors, DR, design, build, implement, and manage Azure systems, while ensuring security, scalability, and dependability.
A8: Azue DevOps Engineer | B8: Total Experience: 5-7 Years. AZ400 Certfied DevOps Engineer. Primary Skills:Proficiency in Azure DevOps or GitHub, continuous integration, continuous delivery, pipelines, and Git version control, Azure Containers Seconary Skills: , AKS, PowerShell and Azure CLI, App Services, Good Knowledge on Azure networking, virtual networks, firewalls, load balancers, and VPNs.
A9: Azure .Net Tech Lad | B9: Total Experience: 7-9 Years Primary Skills: Azure Schedular, Azure Logic App, Azure App Service Plan and App Services, . Net Core, . Net Framework, C#/.Net, ASP.NET, SQL, JavaScript, HTML5, CSS Secondary Skills: DB Development SQL Server, Azure Storage and MS Defender, Azure Funtions, github Good to have: SSO integration, PDF generation using ASP.NET Web application, Azure networking, virtual networks, firewalls, load balancers, and VPNs.
A10: Azure .Net Developer | B10: Total Experience: 4-5 Years Primary Skills: Azure Schedular, Azure Logic App, Azure App Service Plan and App Services, . Net Core, . Net Framework, C#/.Net, ASP.NET, SQL, JavaScript, HTML5, CSS Secondary Skills: DB Development SQL Server, Azure Storage and MS Defender, Azure Funtions, github Good to have: SSO integration, PDF generation using ASP.NET Web application, Azure networking, virtual networks, firewalls, load balancers, and VPNs.
A11: Test Lead | B11: Total Yrs of experience: 7-9 years of overall testing experience with a minimum 4 years experience with APIs, mobile and web app testing, Experience of 4 years or higher in Food&Bevarages and Financial services Test planning: Developing test plans, including the objectives, scope, test levels, test techniques, and resources required Test strategy development: Devising a comprehensive test strategy that outlines the overall approach to testing the software application, Test case review: Reviewing test cases, Overseeing test execution: Coordinating and overseeing the actual testing activities, Defect management: Managing defects, Reporting: Writing reports, Team management: Allocating tasks to team members, monitoring their progress, and providing guidance and support whenever required
A12: Web App Tester | B12: Total Yrs of experience: 4-5 years of overall testing experience with a minimum 6 years experience with APIs, mobile and web app testing, Strong ability to execute functional tests on mobile app with Usability / user experience requirements Experience of 4 years or higher in Food&Bevarages and Financial services
A13: Database Admin | B13: Total Yrs of experience: 7-9 Responsible for a database's performance, integrity, and security Maintain databases with high-availability solutions, replication, backup, restore, encryption, and disaster recovery solutions. Strong database migration experience, Expertise and experience monitoring Azure workspaces, VM's, VM drives, Memory etc.s Monitor system's health and performance, Ensure high levels of performance, availability, sustainability and security Analyze, solve, and correct issues in real time, Provide suggestions for solutions, Refine and automate regular processes, track issues, and document changes, Assist developers with query tuning and schema refinement, Provide 24x7 support for critical production systems, Perform scheduled maintenance and support release deployment activities after hours
... A15: Mobile Developer | B15: Deep knowledge of Android, iOS mobile development, Familiarity with RESTful APIs and mobile libraries for networking, Familiarity with the JSON format, Experience with profiling and debugging mobile applications, Strong knowledge of architectural patterns like MVP, MVC, MVVM, and Clean Architecture and the ability to choose the best solution for the app, Git, Familiarity with push notifications, mobile app design guidelines on each platform, C#..
A16: Pre-Sales Solution Architect

Sheet Working-IND_30
A2: FTE | B2: Role | C2: Experience Level | D2: Duration | E2: Manhours | F2: Monthly Cost/ Pay Rate | G2: Leave Encashment Cost | H2: Public Holiday Cost | I2: Monthly Gratuity Cost | J2: Monthly PF Admin Charges | K2: Monthly Medical Cost | L2: Monthly Payroll Cost | M2: Monthly BGV cost | N2: Shift Allowance | O2: Monthly Cost | P2: Laptop Copsts | Q2: Total Monthly Cost | R2: Marup% | S2: Markup | T2: Monthly BR | U2: Project Cost | V2: Project Revenue | W2: GP | X2: GPM
A3: 0.66666667 | B3: Project Manager | C3: 10+ Years | D3: 9 | E3: =D3*A3*21.75*8 -> 1044 | F3: =3200000/12 -> 266666.67 | G3: =((F3/21.75*10)/12)*1.4 -> 14303.959 | H3: =((F3/30*10)/3)*1.35*0 -> 0 | I3: =F3*4.81% -> 12826.667 | J3: =(F3*55%)*1.36% -> 1994.6667 | K3: =3000/D3 -> 333.33333 | L3: =50 -> 50 | M3: =3500/D3 -> 388.88889 | N3: =10000*0 -> 0 | O3: =SUM(F3:N3) -> 296564.18 | P3: =80000/36 -> 2222.2222 | Q3: =O3+P3 -> 298786.4 | R3: 0.43 | S3: =R3*O3 -> 127522.6 | T3: =S3+Q3 -> 426309 | U3: =Q3*A3*D3 -> 1792718.4 | V3: =T3*A3*D3 -> 2557854 | W3: =V3-U3 -> 765135.59 | X3: =W3/V3 -> 0.29913184
A4: 1 | B4: Senior BA | C4: 6 Years | D4: 9 | E4: =D4*A4*21.75*8 -> 1566 | F4: =2400000/12 -> 200000 | G4: =((F4/21.75*10)/12)*1.4 -> 10727.969 | H4: =((F4/30*10)/3)*1.35*0 -> 0 | I4: =F4*4.81% -> 9620 | J4: =(F4*55%)*1.36% -> 1496 | K4: =3000/D4 -> 333.33333 | L4: =50 -> 50 | M4: =3500/D4 -> 388.88889 | N4: =10000*0 -> 0 | O4: =SUM(F4:N4) -> 222616.19 | P4: =80000/36 -> 2222.2222 | Q4: =O4+P4 -> 224838.41 | R4: 0.43 | S4: =R4*O4 -> 95724.962 | T4: =S4+Q4 -> 320563.38 | U4: =Q4*A4*D4 -> 2023545.7 | V4: =T4*A4*D4 -> 2885070.4 | W4: =V4-U4 -> 861524.66 | X4: =W4/V4 -> 0.29861478
A5: 1 | B5: Presales Solution Architect | C5: 10+ Years | D5: 2 | E5: =D5*A5*21.75*8 -> 348 | F5: =4000000/12 -> 333333.33 | G5: =((F5/21.75*10)/12)*1.4 -> 17879.949 | I5: =F5*4.81% -> 16033.333 | J5: =(F5*55%)*1.36% -> 2493.3333 | K5: =3000/D5 -> 1500 | L5: =50 -> 50 | M5: =3500/D5 -> 1750 | N5: =10000*0 -> 0 | O5: =SUM(F5:N5) -> 373039.95 | P5: =80000/36 -> 2222.2222 | Q5: =O5+P5 -> 375262.17 | R5: 0.43 | S5: =R5*O5 -> 160407.18 | T5: =S5+Q5 -> 535669.35 | U5: =Q5*A5*D5 -> 750524.34 | V5: =T5*A5*D5 -> 1071338.7 | W5: =V5-U5 -> 320814.36 | X5: =W5/V5 -> 0.29945185
A6: 1 | B6: Senior Delivery Manager | C6: 10+ Years | D6: 2 | E6: =D6*A6*21.75*8 -> 348 | F6: =150000 -> 150000 | G6: =((F6/21.75*10)/12)*1.4 -> 8045.977 | I6: =F6*4.81% -> 7215 | J6: =(F6*55%)*1.36% -> 1122 | K6: =3000/D6 -> 1500 | L6: =50 -> 50 | M6: =3500/D6 -> 1750 | N6: =10000*0 -> 0 | O6: =SUM(F6:N6) -> 169682.98 | P6: =80000/36 -> 2222.2222 | Q6: =O6+P6 -> 171905.2 | R6: 0.43 | S6: =R6*O6 -> 72963.68 | T6: =S6+Q6 -> 244868.88 | U6: =Q6*A6*D6 -> 343810.4 | V6: =T6*A6*D6 -> 489737.76 | W6: =V6-U6 -> 145927.36 | X6: =W6/V6 -> 0.29797041
A7: 0.66666667 | B7: Technical Architect | C7: 12 years | D7: 9 | E7: =D7*A7*21.75*8 -> 1044 | F7: =4500000/12 -> 375000 | G7: =((F7/21.75*10)/12)*1.4 -> 20114.943 | H7: =((F7/30*10)/3)*1.35*0 -> 0 | I7: =F7*4.81% -> 18037.5 | J7: =(F7*55%)*1.36% -> 2805 | K7: =3000/D7 -> 333.33333 | L7: =50 -> 50 | M7: =3500/D7 -> 388.88889 | N7: =10000*0 -> 0 | O7: =SUM(F7:N7) -> 416729.66 | P7: =80000/36 -> 2222.2222 | Q7: =O7+P7 -> 418951.89 | R7: 0.43 | S7: =R7*O7 -> 179193.76 | T7: =S7+Q7 -> 598145.64 | U7: =Q7*A7*D7 -> 2513711.3 | V7: =T7*A7*D7 -> 3588873.9 | W7: =V7-U7 -> 1075162.5 | X7: =W7/V7 -> 0.29958215
A8: 1 | B8: .Net Technical Lead | C8: 8+ Years | D8: 8 | E8: =D8*A8*21.75*8 -> 1392 | F8: =(3200000/12) -> 266666.67 | G8: =((F8/21.75*10)/12)*1.4 -> 14303.959 | H8: =((F8/30*10)/3)*1.35*0 -> 0 | I8: =F8*4.81% -> 12826.667 | J8: =(F8*55%)*1.36% -> 1994.6667 | K8: =3000/D8 -> 375 | L8: =50 -> 50 | M8: =3500/D8 -> 437.5 | N8: =10000*0 -> 0 | O8: =SUM(F8:N8) -> 296654.46 | P8: =80000/36 -> 2222.2222 | Q8: =O8+P8 -> 298876.68 | R8: 0.43 | S8: =R8*O8 -> 127561.42 | T8: =S8+Q8 -> 426438.1 | U8: =Q8*A8*D8 -> 2391013.5 | V8: =T8*A8*D8 -> 3411504.8 | W8: =V8-U8 -> 1020491.3 | X8: =W8/V8 -> 0.29913232
A9: 1 | B9: Front End Technical Lead | C9: 10+ Years | D9: 8 | E9: =D9*A9*21.75*8 -> 1392 | F9: =3200000/12 -> 266666.67 | G9: =((F9/21.75*10)/12)*1.4 -> 14303.959 | H9: =((F9/30*10)/3)*1.35*0 -> 0 | I9: =F9*4.81% -> 12826.667 | J9: =(F9*55%)*1.36% -> 1994.6667 | K9: =3000/D9 -> 375 | L9: =50 -> 50 | M9: =3500/D9 -> 437.5 | N9: =10000*0 -> 0 | O9: =SUM(F9:N9) -> 296654.46 | P9: =80000/36 -> 2222.2222 | Q9: =O9+P9 -> 298876.68 | R9: 0.43 | S9: =R9*O9 -> 127561.42 | T9: =S9+Q9 -> 426438.1 | U9: =Q9*A9*D9 -> 2391013.5 | V9: =T9*A9*D9 -> 3411504.8 | W9: =V9-U9 -> 1020491.3 | X9: =W9/V9 -> 0.29913232
A10: 2 | B10: Senior .Net Developer | C10: 5+ Years | D10: 8.5 | E10: =D10*A10*21.75*8 -> 2958 | F10: =2200000/12 -> 183333.33 | G10: =((F10/21.75*10)/12)*1.4 -> 9833.9719 | H10: =((F10/30*10)/3)*1.35*0 -> 0 | I10: =F10*4.81% -> 8818.3333 | J10: =(F10*55%)*1.36% -> 1371.3333 | K10: =3000/D10 -> 352.94118 | L10: =50 -> 50 | M10: =3500/D10 -> 411.76471 | N10: =10000*0 -> 0 | O10: =SUM(F10:N10) -> 204171.68 | P10: =80000/36 -> 2222.2222 | Q10: =O10+P10 -> 206393.9 | R10: 0.43 | S10: =R10*O10 -> 87793.821 | T10: =S10+Q10 -> 294187.72 | U10: =Q10*A10*D10 -> 3508696.3 | V10: =T10*A10*D10 -> 5001191.3 | W10: =V10-U10 -> 1492495 | X10: =W10/V10 -> 0.29842789
A11: 1 | B11: Junior .Net Developer | C11: 3+ Years | D11: 9 | E11: =D11*A11*21.75*8 -> 1566 | F11: =1800000/12 -> 150000 | G11: =((F11/21.75*10)/12)*1.4 -> 8045.977 | H11: =((F11/30*10)/3)*1.35*0 -> 0 | I11: =F11*4.81% -> 7215 | J11: =(F11*55%)*1.36% -> 1122 | K11: =3000/D11 -> 333.33333 | L11: =50 -> 50 | M11: =3500/D11 -> 388.88889 | N11: =10000*0 -> 0 | O11: =SUM(F11:N11) -> 167155.2 | P11: =80000/36 -> 2222.2222 | Q11: =O11+P11 -> 169377.42 | R11: 0.43 | S11: =R11*O11 -> 71876.736 | T11: =S11+Q11 -> 241254.16 | U11: =Q11*A11*D11 -> 1524396.8 | V11: =T11*A11*D11 -> 2171287.4 | W11: =V11-U11 -> 646890.62 | X11: =W11/V11 -> 0.29792952
A12: 0.25 | B12: Database Admin / Architect | C12: 10+ years | D12: 7 | E12: =D12*A12*21.75*8 -> 304.5 | F12: =3600000/12 -> 300000 | G12: =((F12/21.75*10)/12)*1.4 -> 16091.954 | H12: =((F12/30*10)/3)*1.35*0 -> 0 | I12: =F12*4.81% -> 14430 | J12: =(F12*55%)*1.36% -> 2244 | K12: =3000/D12 -> 428.57143 | L12: =50 -> 50 | M12: =3500/D12 -> 500 | N12: =10000*0 -> 0 | O12: =SUM(F12:N12) -> 333744.53 | P12: =80000/36 -> 2222.2222 | Q12: =O12+P12 -> 335966.75 | R12: 0.43 | S12: =R12*O12 -> 143510.15 | T12: =S12+Q12 -> 479476.89 | U12: =Q12*A12*D12 -> 587941.81 | V12: =T12*A12*D12 -> 839084.56 | W12: =V12-U12 -> 251142.76 | X12: =W12/V12 -> 0.29930566
A13: 1 | B13: SQL Developer | C13: 3+ Years | D13: 7 | E13: =D13*A13*21.75*8 -> 1218 | F13: =1000000/12 -> 83333.333 | G13: =((F13/21.75*10)/12)*1.4 -> 4469.9872 | H13: =((F13/30*10)/3)*1.35*0 -> 0 | I13: =F13*4.81% -> 4008.3333 | J13: =(F13*55%)*1.36% -> 623.33333 | K13: =3000/D13 -> 428.57143 | L13: =50 -> 50 | M13: =3500/D13 -> 500 | N13: =10000*0 -> 0 | O13: =SUM(F13:N13) -> 93413.559 | P13: =80000/36 -> 2222.2222 | Q13: =O13+P13 -> 95635.781 | R13: 0.43 | S13: =R13*O13 -> 40167.83 | T13: =S13+Q13 -> 135803.61 | U13: =Q13*A13*D13 -> 669450.47 | V13: =T13*A13*D13 -> 950625.28 | W13: =V13-U13 -> 281174.81 | X13: =W13/V13 -> 0.29577881
A14: 1 | B14: Senior SQL Developer | C14: 5+ Years | D14: 7 | E14: =D14*A14*21.75*8 -> 1218 | F14: =2000000/12 -> 166666.67 | G14: =((F14/21.75*10)/12)*1.4 -> 8939.9745 | H14: =((F14/30*10)/3)*1.35*0 -> 0 | I14: =F14*4.81% -> 8016.6667 | J14: =(F14*55%)*1.36% -> 1246.6667 | K14: =3000/D14 -> 428.57143 | L14: =50 -> 50 | M14: =3500/D14 -> 500 | N14: =10000*0 -> 0 | O14: =SUM(F14:N14) -> 185848.55 | P14: =80000/36 -> 2222.2222 | Q14: =O14+P14 -> 188070.77 | R14: 0.43 | S14: =R14*O14 -> 79914.875 | T14: =S14+Q14 -> 267985.64 | U14: =Q14*A14*D14 -> 1316495.4 | V14: =T14*A14*D14 -> 1875899.5 | W14: =V14-U14 -> 559404.12 | X14: =W14/V14 -> 0.29820581
A15: 1 | B15: Senior UX Designer | C15: 6+ years | D15: 8 | E15: =D15*A15*21.75*8 -> 1392 | F15: =2500000/12 -> 208333.33 | G15: =((F15/21.75*10)/12)*1.4 -> 11174.968 | H15: =((F15/30*10)/3)*1.35*0 -> 0 | I15: =F15*4.81% -> 10020.833 | J15: =(F15*55%)*1.36% -> 1558.3333 | K15: =3000/D15 -> 375 | L15: =50 -> 50 | M15: =3500/D15 -> 437.5 | N15: =10000*0 -> 0 | O15: =SUM(F15:N15) -> 231949.97 | P15: =80000/36 -> 2222.2222 | Q15: =O15+P15 -> 234172.19 | R15: 0.43 | S15: =R15*O15 -> 99738.486 | T15: =S15+Q15 -> 333910.68 | U15: =Q15*A15*D15 -> 1873377.5 | V15: =T15*A15*D15 -> 2671285.4 | W15: =V15-U15 -> 797907.89 | X15: =W15/V15 -> 0.2986981
A16: 1 | B16: Front End Developer | C16: 3+ Years | D16: 7 | E16: =D16*A16*21.75*8 -> 1218 | F16: =2100000/12 -> 175000 | G16: =((F16/21.75*10)/12)*1.4 -> 9386.9732 | H16: =((F16/30*10)/3)*1.35*0 -> 0 | I16: =F16*4.81% -> 8417.5 | J16: =(F16*55%)*1.36% -> 1309 | K16: =3000/D16 -> 428.57143 | L16: =50 -> 50 | M16: =3500/D16 -> 500 | N16: =10000*0 -> 0 | O16: =SUM(F16:N16) -> 195092.04 | P16: =80000/36 -> 2222.2222 | Q16: =O16+P16 -> 197314.27 | R16: 0.43 | S16: =R16*O16 -> 83889.579 | T16: =S16+Q16 -> 281203.85 | U16: =Q16*A16*D16 -> 1381199.9 | V16: =T16*A16*D16 -> 1968426.9 | W16: =V16-U16 -> 587227.05 | X16: =W16/V16 -> 0.29832302
A17: 2 | B17: Senior Front end Developer | C17: 5+ Years | D17: 8 | E17: =D17*A17*21.75*8 -> 2784 | F17: =2700000/12 -> 225000 | G17: =((F17/21.75*10)/12)*1.4 -> 12068.966 | H17: =((F17/30*10)/3)*1.35*0 -> 0 | I17: =F17*4.81% -> 10822.5 | J17: =(F17*55%)*1.36% -> 1683 | K17: =3000/D17 -> 375 | L17: =50 -> 50 | M17: =3500/D17 -> 437.5 | N17: =10000*0 -> 0 | O17: =SUM(F17:N17) -> 250436.97 | P17: =80000/36 -> 2222.2222 | Q17: =O17+P17 -> 252659.19 | R17: 0.43 | S17: =R17*O17 -> 107687.9 | T17: =S17+Q17 -> 360347.08 | U17: =Q17*A17*D17 -> 4042547 | V17: =T17*A17*D17 -> 5765553.3 | W17: =V17-U17 -> 1723006.3 | X17: =W17/V17 -> 0.29884492
A18: 1 | B18: Senior UI Designer | C18: 6+ years | D18: 8 | E18: =D18*A18*21.75*8 -> 1392 | F18: =2700000/12 -> 225000 | G18: =((F18/21.75*10)/12)*1.4 -> 12068.966 | H18: =((F18/30*10)/3)*1.35*0 -> 0 | I18: =F18*4.81% -> 10822.5 | J18: =(F18*55%)*1.36% -> 1683 | K18: =3000/D18 -> 375 | L18: =50 -> 50 | M18: =3500/D18 -> 437.5 | N18: =10000*0 -> 0 | O18: =SUM(F18:N18) -> 250436.97 | P18: =80000/36 -> 2222.2222 | Q18: =O18+P18 -> 252659.19 | R18: 0.43 | S18: =R18*O18 -> 107687.9 | T18: =S18+Q18 -> 360347.08 | U18: =Q18*A18*D18 -> 2021273.5 | V18: =T18*A18*D18 -> 2882776.7 | W18: =V18-U18 -> 861503.16 | X18: =W18/V18 -> 0.29884492
A19: 1 | B19: Azure Cloud Architect | C19: 10+ Years | D19: 3 | E19: =D19*A19*21.75*8 -> 522 | F19: =3800000/12 -> 316666.67 | G19: =((F19/21.75*10)/12)*1.4 -> 16985.951 | H19: =((F19/30*10)/3)*1.35*0 -> 0 | I19: =F19*4.81% -> 15231.667 | J19: =(F19*55%)*1.36% -> 2368.6667 | K19: =3000/D19 -> 1000 | L19: =50 -> 50 | M19: =3500/D19 -> 1166.6667 | N19: =10000*0 -> 0 | O19: =SUM(F19:N19) -> 353469.62 | P19: =80000/36 -> 2222.2222 | Q19: =O19+P19 -> 355691.84 | R19: 0.43 | S19: =R19*O19 -> 151991.94 | T19: =S19+Q19 -> 507683.78 | U19: =Q19*A19*D19 -> 1067075.5 | V19: =T19*A19*D19 -> 1523051.3 | W19: =V19-U19 -> 455975.81 | X19: =W19/V19 -> 0.29938309
A20: 1 | B20: Senior Devops Engineer | C20: 6+ Years | D20: 6 | E20: =D20*A20*21.75*8 -> 1044 | F20: =2500000/12 -> 208333.33 | G20: =((F20/21.75*10)/12)*1.4 -> 11174.968 | H20: =((F20/30*10)/3)*1.35*0 -> 0 | I20: =F20*4.81% -> 10020.833 | J20: =(F20*55%)*1.36% -> 1558.3333 | K20: =3000/D20 -> 500 | L20: =50 -> 50 | M20: =3500/D20 -> 583.33333 | N20: =10000*0 -> 0 | O20: =SUM(F20:N20) -> 232220.8 | P20: =80000/36 -> 2222.2222 | Q20: =O20+P20 -> 234443.02 | R20: 0.43 | S20: =R20*O20 -> 99854.945 | T20: =S20+Q20 -> 334297.97 | U20: =Q20*A20*D20 -> 1406658.1 | V20: =T20*A20*D20 -> 2005787.8 | W20: =V20-U20 -> 599129.67 | X20: =W20/V20 -> 0.29870042
A21: 1 | B21: Test Lead | C21: 8+ Years | D21: 7 | E21: =D21*A21*21.75*8 -> 1218 | F21: =2700000/12 -> 225000 | G21: =((F21/21.75*10)/12)*1.4 -> 12068.966 | H21: =((F21/30*10)/3)*1.35*0 -> 0 | I21: =F21*4.81% -> 10822.5 | J21: =(F21*55%)*1.36% -> 1683 | K21: =3000/D21 -> 428.57143 | L21: =50 -> 50 | M21: =3500/D21 -> 500 | N21: =10000*0 -> 0 | O21: =SUM(F21:N21) -> 250553.04 | P21: =80000/36 -> 2222.2222 | Q21: =O21+P21 -> 252775.26 | R21: 0.43 | S21: =R21*O21 -> 107737.81 | T21: =S21+Q21 -> 360513.07 | U21: =Q21*A21*D21 -> 1769426.8 | V21: =T21*A21*D21 -> 2523591.5 | W21: =V21-U21 -> 754164.64 | X21: =W21/V21 -> 0.29884577
A22: 1 | B22: Jr Test Engineer | C22: 1-3 Years | D22: 7 | E22: =D22*A22*21.75*8 -> 1218 | F22: =1100000/12 -> 91666.667 | G22: =((F22/21.75*10)/12)*1.4 -> 4916.986 | H22: =((F22/30*10)/3)*1.35*0 -> 0 | I22: =F22*4.81% -> 4409.1667 | J22: =(F22*55%)*1.36% -> 685.66667 | K22: =3000/D22 -> 428.57143 | L22: =50 -> 50 | M22: =3500/D22 -> 500 | N22: =10000*0 -> 0 | O22: =SUM(F22:N22) -> 102657.06 | P22: =80000/36 -> 2222.2222 | Q22: =O22+P22 -> 104879.28 | R22: 0.43 | S22: =R22*O22 -> 44142.535 | T22: =S22+Q22 -> 149021.81 | U22: =Q22*A22*D22 -> 734154.96 | V22: =T22*A22*D22 -> 1043152.7 | W22: =V22-U22 -> 308997.74 | X22: =W22/V22 -> 0.29621525
A23: 1 | B23: Senior Test Engineer | C23: 5+ Years | D23: 7 | E23: =D23*A23*21.75*8 -> 1218 | F23: =2000000/12 -> 166666.67 | G23: =((F23/21.75*10)/12)*1.4 -> 8939.9745 | H23: =((F23/30*10)/3)*1.35*0 -> 0 | I23: =F23*4.81% -> 8016.6667 | J23: =(F23*55%)*1.36% -> 1246.6667 | K23: =3000/D23 -> 428.57143 | L23: =50 -> 50 | M23: =3500/D23 -> 500 | N23: =10000*0 -> 0 | O23: =SUM(F23:N23) -> 185848.55 | P23: =80000/36 -> 2222.2222 | Q23: =O23+P23 -> 188070.77 | R23: 0.43 | S23: =R23*O23 -> 79914.875 | T23: =S23+Q23 -> 267985.64 | U23: =Q23*A23*D23 -> 1316495.4 | V23: =T23*A23*D23 -> 1875899.5 | W23: =V23-U23 -> 559404.12 | X23: =W23/V23 -> 0.29820581
A24: 1 | B24: Senior Mobile Developer | C24: 6+ years | D24: 6 | E24: =D24*A24*21.75*8 -> 1044 | F24: =2000000/12 -> 166666.67 | G24: =((F24/21.75*10)/12)*1.4 -> 8939.9745 | H24: =((F24/30*10)/3)*1.35*0 -> 0 | I24: =F24*4.81% -> 8016.6667 | J24: =(F24*55%)*1.36% -> 1246.6667 | K24: =3000/D24 -> 500 | L24: =50 -> 50 | M24: =3500/D24 -> 583.33333 | N24: =10000*0 -> 0 | O24: =SUM(F24:N24) -> 186003.31 | P24: =80000/36 -> 2222.2222 | Q24: =O24+P24 -> 188225.53 | R24: 0.43 | S24: =R24*O24 -> 79981.422 | T24: =S24+Q24 -> 268206.95 | U24: =Q24*A24*D24 -> 1129353.2 | V24: =T24*A24*D24 -> 1609241.7 | W24: =V24-U24 -> 479888.53 | X24: =W24/V24 -> 0.29820786
A25: =SUM(A3:A24) -> 22.583333 | F25: =SUM(F3:F24) -> 4750000 | G25: =SUM(G3:G24) -> 254789.27 | H25: =SUM(H3:H24) -> 0 | I25: =SUM(I3:I24) -> 228475 | J25: =SUM(J3:J24) -> 35530 | K25: =SUM(K3:K24) -> 11561.275 | L25: =SUM(L3:L24) -> 1100 | M25: =SUM(M3:M24) -> 13488.154 | ... Q25: =SUM(Q3:Q24) -> 5343832.6 | S25: =SUM(S3:S24) -> 2276825.8 | T25: =SUM(T3:T24) -> 7620658.4 | U25: =SUM(U3:U24) -> 36554880 | V25: =SUM(V3:V24) -> 52122739 | W25: =SUM(W3:W24) -> 15567859 | X25: =W25/V25 -> 0.29867692
T27: Non People Cost
T28: Travel | U28: =N35 -> 0
T29: POC Cost
T31: Total Cost | U31: =SUM(U25:U29) -> 36554880 | V31: =SUM(V25:V28) -> 52122739 | W31: =V31-U31 -> 15567859
V35: INR Currency | W35: PHP Currency
U36: Revenue | V36: =V31 -> 52122739 | W36: =V36/1.48 -> 35218067
U37: Cost | V37: =U31 -> 36554880 | W37: =V37/1.48 -> 24699243
U38: GP | V38: =V36-V37 -> 15567859 | W38: =W36-W37 -> 10518824
U39: GPM for the Project | V39: =V38/V36 -> 0.29867692 | W39: =W38/W36 -> 0.29867692

Sheet Login Details
A1: CWT | B1: Dev : https://cocacolaph-dev.outsystemsenterprise.com/CWT | C1: c-chris.lugue@coca-cola.com.ph | E1: Cokewilkins1234* | F1: Admin
A3: Digitizing CAF | B3: https://cocacolaph-tst.outsystemsenterprise.com/CAF_Internal | C3: CAF_Admin@cocacola.com | E3: P@ssw0rd123 | F3: Admin
B4: https://cocacolaph-tst.outsystemsenterprise.com/CustomerManagement/ | F4: Customer
A7: Site Admin
A9: Dev : https://cocacolaph-dev.outsystemsenterprise.com/CWT
A11: Uname - c-sanjay.mahadevanayaka@coca-cola.com.ph
A13: Password - !Coke@1044407
A16: TaxLead
A18: Uname - c-chethan.chandrashekhar@coca-cola.com.ph
A20: Pass - G0wd@Ch3t#@n7
A22: Pausechallenge833
A24: https://www.youtube.com/watch?v=HfyAxPvBwIE
A26: https://collaberadigitaltechnology.sharepoint.com/sites/CES-CCBPI_Transition/Shared%20Documents/Forms/AllItems.aspx?csf=1&web=1&e=cecRAP&ovuser=3d089d0c%2Dc75a%2D4ec9%2D8abc%2D782fc5b42299%2Cc%2Daparupa%2Esengupta%40coca%2Dcola%2Ecom%2Eph&OR=Teams%2DHL&CT=1711609148560&clickparams=eyJBcHBOYW1lIjoiVGVhbXMtRGVza3RvcCIsIkFwcFZlcnNpb24iOiIxNDE1LzI0MDIyOTIwNjAyIiwiSGFzRmVkZXJhdGVkVXNlciI6ZmFsc2V9&cid=a62b8270%2D6bfa%2D47d5%2Db3a2%2D7cf5a2fb0e19&FolderCTID=0x012000991DD73A1A074D469F0B54148D6EE395&id=%2Fsites%2FCES%2DCCBPI%5FTransition%2FShared%20Documents%2FOut%20System%20Migration%2FInternal%20Document%20Sharing&viewid=eb4f162e%2Dc5b9%2D4a7c%2Db58e%2D7e07228ec85b
A28: Coke Survey App is used to conduct surveys, to manage survey questions and to manage survey results.
A29: Site Admin
A34: CWT | B34: Dev : https://cocacolaph-dev.outsystemsenterprise.com/CWT | C34: c-chris.lugue@coca-cola.com.ph | E34: Cokewilkins1234* | F34: Admin
A40: Digitizing CAF | B40: https://cocacolaph-tst.outsystemsenterprise.com/CAF_Internal | C40: CAF_Admin@cocacola.com | E40: P@ssw0rd123 | F40: Admin
A41: https://cocacolaph-tst.outsystemsenterprise.com/CustomerManagement/ | C41: Customer
A45: Dev : https://cocacolaph-dev.outsystemsenterprise.com/CWT
A46: Uname - c-sanjay.mahadevanayaka@coca-cola.com.ph
A47: Password - !Coke@1044407
A49: TaxLead
A50: Uname - c-chethan.chandrashekhar@coca-cola.com.ph
A51: Pass - G0wd@Ch3t#@n7
A56: Admin : Configuration
A57: https://cocacolaph-dev.outsystemsenterprise.com/CAF_Common/Login
A58: User name : CAF_Admin@cocacola.com
A59: Password : P@ssw0rd123
A60: Approver Email ID: reynaldo.abellera@coca-cola.com.ph/jayson.catacutan@dbresults.com.hk
A62: Admin Customer confi:
... A69: User Name: Approver/Customer mail - 502147751

Sheet Survey Details
E1: PM | F1: BA | G1: Architect | H1: Tech Lead | I1: Dev1 | J1: Dev2 | K1: Test Lead | L1: Test Engineer | M1: DBA | N1: DB Developer | O1: UX | P1: UI | Q1: Cloud Architect | R1: DevOps Engineer
A2: Surveys
B3: Dash Board & List View | E3: 2 | F3: 3 | G3: 3 | H3: 3 | I3: 5 | J3: 5 | K3: 3 | L3: 5 | M3: 1 | N3: 3 | O3: 2 | P3: 3
C4: Search
C5: Create Survey
C6: Add section
C7: Add Question | E7: 4 | F7: 4 | G7: 4 | H7: 5 | I7: 8 | J7: 8 | K7: 3 | L7: 6 | M7: 5 | N7: 8 | O7: 6 | P7: 8
D8: Question display
D9: Select type of question
D10: Edit question
D11: Delete question
D12: Change question type
D13: Move to section
D14: Question display
C15: Edit Survey | E15: 4 | F15: 4 | G15: 4 | H15: 5 | I15: 8 | J15: 8 | K15: 3 | L15: 6 | M15: 5 | N15: 8 | O15: 6 | P15: 8
D16: Add section
D17: Add Question | E17: 1 | F17: 1 | G17: 1 | H17: 1 | I17: 3 | J17: 3 | K17: 2 | L17: 3 | M17: 1 | N17: 3 | O17: 2 | P17: 2
D18: Select type of question
D19: Edit question
D20: Delete question
D21: Change question type
D22: Move to section
C23: Duplicate survey | E23: 1 | F23: 1 | G23: 1 | H23: 1 | I23: 2 | J23: 2 | K23: 1 | L23: 2 | M23: 1 | N23: 1 | O23: 1 | P23: 1
D24: Pubish Survey | E24: 1 | F24: 1 | G24: 1 | H24: 1 | I24: 3 | J24: 3 | K24: 1 | L24: 3 | M24: 1 | N24: 1 | O24: 1 | P24: 1
C25: Close survey
C26: View respondents | E26: 1 | F26: 1 | G26: 1 | H26: 1 | I26: 3 | J26: 3 | K26: 2 | L26: 3 | M26: 1 | N26: 3 | O26: 2 | P26: 2
D27: List view
D28: View survey response
C29: Preview survey | E29: 1 | F29: 1 | G29: 1 | H29: 1 | I29: 2 | J29: 2 | K29: 1 | L29: 2 | M29: 1 | N29: 1 | O29: 1 | P29: 1
C30: Download survey report
E31: =SUM(E2:E29) -> 15 | F31: =SUM(F2:F29) -> 16 | G31: =SUM(G2:G29) -> 16 | H31: =SUM(H2:H29) -> 18 | I31: =SUM(I2:I29) -> 34 | J31: =SUM(J2:J29) -> 34 | K31: =SUM(K2:K29) -> 16 | L31: =SUM(L2:L29) -> 30 | ... R31: =SUM(R2:R29) -> 0

Sheet DI Audit logs Details
A1: Audit Logs | E1: =SUM(E2:E11) -> 4 | F1: =SUM(F2:F11) -> 4 | G1: =SUM(G2:G11) -> 4 | H1: =SUM(H2:H11) -> 8 | I1: =SUM(I2:I11) -> 12 | J1: =SUM(J2:J11) -> 12 | K1: =SUM(K2:K11) -> 8 | L1: =SUM(L2:L11) -> 12 | ... P1: =SUM(P2:P11) -> 8
B2: Print Log | C2: Filter Search | E2: 1 | F2: 1 | G2: 1 | H2: 2 | I2: 3 | J2: 3 | K2: 2 | L2: 3 | M2: 1 | N2: 2 | O2: 2 | P2: 2
C3: Export Report
C4: List View
B5: Approver Log | C5: Filter Search | E5: 1 | F5: 1 | G5: 1 | H5: 2 | I5: 3 | J5: 3 | K5: 2 | L5: 3 | M5: 1 | N5: 2 | O5: 2 | P5: 2
C6: Export Report
C7: List View
B8: Email Log | C8: Filter Search | E8: 1 | F8: 1 | G8: 1 | H8: 2 | I8: 3 | J8: 3 | K8: 2 | L8: 3 | M8: 1 | N8: 2 | O8: 2 | P8: 2
C9: Export Report
C10: List View
B11: Invoice Log | C11: Filter Search | E11: 1 | F11: 1 | G11: 1 | H11: 2 | I11: 3 | J11: 3 | K11: 2 | L11: 3 | M11: 1 | N11: 2 | O11: 2 | P11: 2
C12: Export Report
C13: List View
